Workbook

Sheet Intro & Core Assumptions
B4: Company Description | C4: Sun Pharmaceutical Industries Ltd
B5: ISIN Code | C5: INE044A01036
B6: Sector Name | C6: Healthcare
B7: Industry | C7: Pharmaceutical
B8: Exchange Name | C8: BSE: 524715, NSE: SUNPHARMA
B9: Website | C9: hhttps://sunpharma.com/
B10: Company Description | C10: Sun Pharmaceutical Industries Ltd is engaged in the business of manufacturing, developing and marketing a wide range of branded and generic formulations and Active Pharma Ingredients (APIs). The company and its subsidiaries has various manufacturing facilities spread across the world with trading and other incidental and related activities extending to global market.It is the largest pharmaceutical company in India.
B11: Current Market Price | C11: 1840
B14: Scenario | D14: Case
B15: Base case | D15: =IF(B15="Best case",1,IF(B15="Base case",2,3)) -> 2
B18: Company data
B19: Particulars | D19: Amount
B20: No of Outstanding shares | C20: Nos | D20: 2406292857
B21: Face Value per share | C21: Rs. | D21: 1
B22: Current Market Price | C22: Rs. | D22: =C11 -> 1840
B23: Market Capitalisation | C23: INR in crs | D23: =D20*D22/10^7 -> 442757.89
B25: Assumptions
B26: Increase in Sales volume growth rate | C26: % | D26: =Assumptions!G10 -> 0.084161961
B27: Perpetual Growth rate | C27: % | D27: ='DCF Valuation'!C26 -> 0.04
B28: 10 year Bond yield rate | C28: % | D28: =WACC!K27 -> 0.0689
B29: Interest rate | C29: % | D29: =Assumptions!G15 -> 0.081301899
B30: Pharma sector growth rate (25-30) | C30: % | D30: 0.1
B32: Company Sales volume data
B33: Year | D33: Revenue in Crs
B34: 2021 | D34: 33498.14
B35: =B34+1 -> 2022 | D35: 38654.49
B36: =B35+1 -> 2023 | D36: 43885.68
B37: =B36+1 -> 2024 | D37: 48496.85
B38: =B37+1 -> 2025 | D38: 52578.44
B41: Sheet | C41: Assumptions
B42: Revenue Buildup | C42: Revenue is increasing by 10% (base case) from 2025 to 2030 (according to IBEF ) after that the growth rate is tapered by 12.25% every year till 2035 when it reaches to 4% perpetual growth rate.
C43: Bull case growth rate is taken as +5% of base case and worst case growth rate is taken as -5% of base case.
B44: Income Statement | C44: All costs except finance costs, tax, and depreciation have been forecasted as a % of Total Revenue and using the average percantage of historical years for forecasting.
C45: Finance costs have been forecasted as a % of the sum of long-term and short-term borrowings using the latest year’s percentage.
C46: Tax expense has been forecasted by increasing the effective tax rate (calculated as a % of PBT) by 1% and then increase by 1% after every 2 years.
C47: Dividend has been forecasted using the average percentage of last 3 years and then multiply that percentage with current PAT.
C48: Depreciation and ammortization has been forecasted by using latest deprecaiation on Fixed Assets and the increasing it by 1% and then increasing by 1% once after every 2 years.
C49: Other Income has been forecasted as the average % of sales of the last three years, while the share of profit/loss from associates and joint ventures has been forecasted using the average % of the last five years.
B50: Balance Sheet | C50: PPE has been calculated as per its schedule, while Trade Receivables have been forecasted as the average % of sales of historical years, and Inventories and Trade Payables have been forecasted as a % of COGS of historical years.
C51: Reserves have been forecasted based on the previous year’s reserves, after adding retained earnings generated from net profit after dividend distribution.
C52: Cash and Cash equivalents are forecasted in Cash Flow Statement
C53: All other assets and liabilities have been assumed to remain constant over the forecast period.
B54: DCF Analysis | C54: The terminal value has been estimated using the FCFF of the final forecasted year and applying the Gordon Growth Model to the free cash flow.
C55: The Buy and Ignore recommendation is based on a comparison between the Target Price and CMP. If the Target Price is lower than the CMP, the recommendation is “Ignore”; otherwise, it is “Buy.”
C56: Sensitivity Analysis has been conducted to evaluate the impact of changes in key assumptions on the target price derived from the DCF model. The analysis considers variations in WACC and Terminal Growth Rate.
B57: Comparable Valuation | C57: Median valuation multiples have been used to derive the company’s relative valuation, ensuring consistency and comparability across peers.
B58: WACC | C58: The target capital structure and calculated beta have been used to determine the company’s WACC.
B59: Equity Beta | C59: The company’s 10-year share price movement has been compared with the one-year Nifty 50 index performance to calculate the company’s beta.
B60: Market Return | C60: Market return has been derived using the long-term average returns of the Nifty 50 over the last 10 years and calculated using the 10-year CAGR.
B61: Ratio Analysis | C61: Ratio interpretations are based on the Base Case figures. However, when assumptions are adjusted for bull or worst case scenarios, the interpreted figures may vary accordingly to reflect the impact of those scenarios.
B62: Summary | C62: A football field chart has been prepared to summarize the valuation by illustrating four key perspectives: Comparable Company Valuation, 52-Week High-Low Range, DCF Valuation, and Market Consensus, providing a comprehensive view of the company’s valuation range.

Sheet Assumptions
B7: Particulars | C7: Historical | H7: Forecasting
C8: 44286 | D8: 44651 | E8: 45016 | F8: 45382 | G8: 45747 | H8: 46112 | I8: 46477 | J8: 46843 | K8: 47208 | L8: 47573 | M8: =L8+365 -> 47938 | N8: =M8+365 -> 48303 | O8: =N8+365 -> 48668 | P8: =O8+365 -> 49033 | Q8: =P8+365 -> 49398
H9: Base Case
B10: Sales Growth (y-o-y increase) | C10: - | D10: =('Income Statement'!D9-'Income Statement'!C9)/'Income Statement'!C9 -> 0.15392944 | E10: =('Income Statement'!E9-'Income Statement'!D9)/'Income Statement'!D9 -> 0.13533201 | F10: =('Income Statement'!F9-'Income Statement'!E9)/'Income Statement'!E9 -> 0.10507232 | G10: =('Income Statement'!G9-'Income Statement'!F9)/'Income Statement'!F9 -> 0.084161961 | H10: =IF($H$9="Base Case",'Revenue Buildup'!E8,IF(Assumptions!$H$9="Bull Case",'Revenue Buildup'!E9,'Revenue Buildup'!E10)) -> 0.1 | I10: =IF($H$9="Base Case",'Revenue Buildup'!F8,IF(Assumptions!$H$9="Bull Case",'Revenue Buildup'!F9,'Revenue Buildup'!F10)) -> 0.1 | J10: =IF($H$9="Base Case",'Revenue Buildup'!G8,IF(Assumptions!$H$9="Bull Case",'Revenue Buildup'!G9,'Revenue Buildup'!G10)) -> 0.1 | K10: =IF($H$9="Base Case",'Revenue Buildup'!H8,IF(Assumptions!$H$9="Bull Case",'Revenue Buildup'!H9,'Revenue Buildup'!H10)) -> 0.1 | L10: =IF($H$9="Base Case",'Revenue Buildup'!I8,IF(Assumptions!$H$9="Bull Case",'Revenue Buildup'!I9,'Revenue Buildup'!I10)) -> 0.1 | M10: =IF($H$9="Base Case",'Revenue Buildup'!J8,IF(Assumptions!$H$9="Bull Case",'Revenue Buildup'!J9,'Revenue Buildup'!J10)) -> 0.08325 | N10: =IF($H$9="Base Case",'Revenue Buildup'!K8,IF(Assumptions!$H$9="Bull Case",'Revenue Buildup'!K9,'Revenue Buildup'!K10)) -> 0.069305625 | O10: =IF($H$9="Base Case",'Revenue Buildup'!L8,IF(Assumptions!$H$9="Bull Case",'Revenue Buildup'!L9,'Revenue Buildup'!L10)) -> 0.057696933 | ... Q10: =IF($H$9="Base Case",'Revenue Buildup'!N8,IF(Assumptions!$H$9="Bull Case",'Revenue Buildup'!N9,'Revenue Buildup'!N10)) -> 0.03998722
B11: Cost of goods Sold (% of sales) | C11: ='Income Statement'!C10/'Income Statement'!C9 -> 0.25941978 | D11: ='Income Statement'!D10/'Income Statement'!D9 -> 0.26779657 | E11: ='Income Statement'!E10/'Income Statement'!E9 -> 0.24295305 | F11: ='Income Statement'!F10/'Income Statement'!F9 -> 0.21986191 | G11: ='Income Statement'!G10/'Income Statement'!G9 -> 0.20440622 | H11: =AVERAGE(C11:G11) -> 0.23888751 | I11: =H11 -> 0.23888751 | J11: =I11 -> 0.23888751 | K11: =J11 -> 0.23888751 | L11: =K11 -> 0.23888751 | M11: =L11 -> 0.23888751 | N11: =M11 -> 0.23888751 | O11: =N11 -> 0.23888751 | P11: =O11 -> 0.23888751 | Q11: =P11 -> 0.23888751
B12: Employee Cost (% of sales) | C12: ='Income Statement'!C12/'Income Statement'!C9 -> 0.20485406 | D12: ='Income Statement'!D12/'Income Statement'!D9 -> 0.18887405 | E12: ='Income Statement'!E12/'Income Statement'!E9 -> 0.18903729 | F12: ='Income Statement'!F12/'Income Statement'!F9 -> 0.19442624 | G12: ='Income Statement'!G12/'Income Statement'!G9 -> 0.18968079 | H12: =AVERAGE(C12:G12) -> 0.19337448 | I12: =H12 -> 0.19337448 | J12: =I12 -> 0.19337448 | K12: =J12 -> 0.19337448 | L12: =K12 -> 0.19337448 | M12: =L12 -> 0.19337448 | N12: =M12 -> 0.19337448 | O12: =N12 -> 0.19337448 | P12: =O12 -> 0.19337448 | Q12: =P12 -> 0.19337448
B13: Selling,Admin & Other Expenses (% of Sales) | C13: ='Income Statement'!C13/'Income Statement'!C9 -> 0.28294437 | D13: ='Income Statement'!D13/'Income Statement'!D9 -> 0.2783211 | E13: ='Income Statement'!E13/'Income Statement'!E9 -> 0.29974698 | F13: ='Income Statement'!F13/'Income Statement'!F9 -> 0.31792127 | G13: ='Income Statement'!G13/'Income Statement'!G9 -> 0.31898626 | H13: =AVERAGE(C13:G13) -> 0.29958399 | I13: =H13 -> 0.29958399 | J13: =I13 -> 0.29958399 | K13: =J13 -> 0.29958399 | L13: =K13 -> 0.29958399 | M13: =L13 -> 0.29958399 | N13: =M13 -> 0.29958399 | O13: =N13 -> 0.29958399 | P13: =O13 -> 0.29958399 | Q13: =P13 -> 0.29958399
B14: Depreciation & Ammortization (% of Fixed Assets) | C14: ='Income Statement'!C15/Schedules!C18 -> 0.16889648 | D14: ='Income Statement'!D15/'Balance Sheet'!D11 -> 0.20945209 | E14: ='Income Statement'!E15/'Balance Sheet'!E11 -> 0.24388558 | F14: ='Income Statement'!F15/'Balance Sheet'!F11 -> 0.24605837 | G14: ='Income Statement'!G15/'Balance Sheet'!G11 -> 0.25267947 | H14: =G14*(101%) -> 0.25520626 | I14: =H14 -> 0.25520626 | J14: =I14*(101%) -> 0.25775833 | K14: =J14 -> 0.25775833 | L14: =K14*(101%) -> 0.26033591 | M14: =L14 -> 0.26033591 | N14: =M14*(101%) -> 0.26293927 | O14: =N14 -> 0.26293927 | P14: =O14*(101.5%) -> 0.26688336 | Q14: =P14 -> 0.26688336
B15: Interest Rate (% of Debt) | C15: =Schedules!C27/Schedules!C24 -> 0.042305805 | D15: =Schedules!D27/Schedules!D24 -> 0.036143245 | E15: =Schedules!E27/Schedules!E24 -> 0.18480912 | F15: =Schedules!F27/Schedules!F24 -> 0.03847606 | G15: =Schedules!G27/Schedules!G24 -> 0.081301899 | H15: =G15 -> 0.081301899 | I15: =H15 -> 0.081301899 | J15: =I15 -> 0.081301899 | K15: =J15 -> 0.081301899 | L15: =K15 -> 0.081301899 | M15: =L15 -> 0.081301899 | N15: =M15 -> 0.081301899 | O15: =N15 -> 0.081301899 | ... Q15: =P15 -> 0.081301899
B16: Dividend Payout Ratio (% of PAT) | C16: =-(CFS!D38/'Income Statement'!C22) -> 0.69803067 | D16: =-(CFS!E38/'Income Statement'!D22) -> 0.64001499 | E16: =-(CFS!F38/'Income Statement'!E22) -> 0.29598822 | F16: =-(CFS!G38/'Income Statement'!F22) -> 0.30184193 | G16: =-(CFS!H38/'Income Statement'!G22) -> 0.32990264 | H16: =AVERAGE(E16:G16) -> 0.30924427 | I16: =H16 -> 0.30924427 | J16: =I16 -> 0.30924427 | K16: =J16 -> 0.30924427 | L16: =K16 -> 0.30924427 | M16: =L16 -> 0.30924427 | N16: =M16 -> 0.30924427 | O16: =N16 -> 0.30924427 | P16: =O16 -> 0.30924427 | Q16: =P16 -> 0.30924427
A17: 42500 | B17: Other Income (% of Revenue) | C17: - | D17: - | E17: ='Income Statement'!E18/'Income Statement'!E9 -> 0.0076783589 | F17: ='Income Statement'!F18/'Income Statement'!F9 -> 0.018475427 | G17: ='Income Statement'!G18/'Income Statement'!G9 -> 0.02800996 | H17: =AVERAGE(E17:G17) -> 0.018054582 | I17: =H17 -> 0.018054582 | J17: =I17 -> 0.018054582 | K17: =J17 -> 0.018054582 | L17: =K17 -> 0.018054582 | M17: =L17 -> 0.018054582 | N17: =M17 -> 0.018054582 | O17: =N17 -> 0.018054582 | P17: =O17 -> 0.018054582 | Q17: =P17 -> 0.018054582
B18: Tax Rate (% of PBT) | C18: ='Income Statement'!C20/'Income Statement'!C19 -> 0.18385923 | D18: ='Income Statement'!D20/'Income Statement'!D19 -> 0.23999625 | E18: ='Income Statement'!E20/'Income Statement'!E19 -> 0.090088357 | F18: ='Income Statement'!F20/'Income Statement'!F19 -> 0.12982181 | G18: ='Income Statement'!G20/'Income Statement'!G19 -> 0.20157096 | H18: =G18*(101%) -> 0.20358667 | I18: =H18 -> 0.20358667 | J18: =I18*(101%) -> 0.20562253 | K18: =J18 -> 0.20562253 | L18: =K18*(101%) -> 0.20767876 | M18: =L18 -> 0.20767876 | N18: =M18*(101%) -> 0.20975555 | O18: =N18 -> 0.20975555 | P18: =O18*(101%) -> 0.2118531 | Q18: =P18 -> 0.2118531
B19: Share of (loss)/gain of associates or JV (% of sales) | C19: ='Income Statement'!C21/'Income Statement'!C9 -> -0.00036808014 | D19: ='Income Statement'!D21/'Income Statement'!D9 -> -0.00042789337 | E19: ='Income Statement'!E21/'Income Statement'!E9 -> -0.0010914722 | F19: ='Income Statement'!F21/'Income Statement'!F9 -> -0.0007920102 | G19: ='Income Statement'!G21/'Income Statement'!G9 -> -0.00029194476 | H19: =AVERAGE(C19:G19) -> -0.00059428014 | I19: =H19 -> -0.00059428014 | J19: =I19 -> -0.00059428014 | K19: =J19 -> -0.00059428014 | L19: =K19 -> -0.00059428014 | M19: =L19 -> -0.00059428014 | N19: =M19 -> -0.00059428014 | O19: =N19 -> -0.00059428014 | P19: =O19 -> -0.00059428014 | Q19: =P19 -> -0.00059428014
B20: Inventories days | C20: =('Balance Sheet'!D18/'Income Statement'!C10)*365 -> 377.89207 | D20: =('Balance Sheet'!E18/'Income Statement'!D10)*365 -> 317.23161 | E20: =('Balance Sheet'!F18/'Income Statement'!E10)*365 -> 359.89549 | F20: =('Balance Sheet'!G18/'Income Statement'!F10)*365 -> 337.80902 | G20: =('Balance Sheet'!H18/'Income Statement'!G10)*365 -> 347.88222 | H20: =AVERAGE(C20:G20) -> 348.14208 | I20: =H20 -> 348.14208 | J20: =I20 -> 348.14208 | K20: =J20 -> 348.14208 | L20: =K20 -> 348.14208 | M20: =L20 -> 348.14208 | N20: =M20 -> 348.14208 | O20: =N20 -> 348.14208 | P20: =O20 -> 348.14208 | Q20: =P20 -> 348.14208
B21: Trade receivables days | C21: =('Balance Sheet'!D20/'Income Statement'!C9)*365 -> 98.734169 | D21: =('Balance Sheet'!E20/'Income Statement'!D9)*365 -> 100.02473 | E21: =('Balance Sheet'!F20/'Income Statement'!E9)*365 -> 95.134817 | F21: =('Balance Sheet'!G20/'Income Statement'!F9)*365 -> 84.665706 | G21: =('Balance Sheet'!H20/'Income Statement'!G9)*365 -> 90.566212 | H21: =AVERAGE(C21:G21) -> 93.825126 | I21: =H21 -> 93.825126 | J21: =I21 -> 93.825126 | K21: =J21 -> 93.825126 | L21: =K21 -> 93.825126 | M21: =L21 -> 93.825126 | N21: =M21 -> 93.825126 | O21: =N21 -> 93.825126 | P21: =O21 -> 93.825126 | Q21: =P21 -> 93.825126
B22: Trade Payables days | C22: =('Balance Sheet'!D48/'Income Statement'!C10)*365 -> 166.90133 | D22: =('Balance Sheet'!E48/'Income Statement'!D10)*365 -> 157.94356 | E22: =('Balance Sheet'!F48/'Income Statement'!E10)*365 -> 194.49669 | F22: =('Balance Sheet'!G48/'Income Statement'!F10)*365 -> 193.52246 | G22: =('Balance Sheet'!H48/'Income Statement'!G10)*365 -> 210.0315 | H22: =AVERAGE(C22:G22) -> 184.57911 | I22: =H22 -> 184.57911 | J22: =I22 -> 184.57911 | K22: =J22 -> 184.57911 | L22: =K22 -> 184.57911 | M22: =L22 -> 184.57911 | N22: =M22 -> 184.57911 | O22: =N22 -> 184.57911 | P22: =O22 -> 184.57911 | Q22: =P22 -> 184.57911

Sheet Revenue Buildup
B7: Revenue Scenarios | C7: Growth (%) | E7: 46112 | F7: 46477 | G7: 46843 | H7: 47208 | I7: 47573 | J7: =I7+365 -> 47938 | K7: =J7+365 -> 48303 | L7: =K7+365 -> 48668 | M7: =L7+365 -> 49033 | N7: =M7+365 -> 49398
B8: Base Case | C8: ='Intro & Core Assumptions'!D30 -> 0.1 | E8: =C8 -> 0.1 | F8: =E8 -> 0.1 | G8: =F8 -> 0.1 | H8: =G8 -> 0.1 | I8: =H8 -> 0.1 | J8: =I8*(1-$C$11) -> 0.08325 | K8: =J8*(1-$C$11) -> 0.069305625 | L8: =K8*(1-$C$11) -> 0.057696933 | M8: =L8*(1-$C$11) -> 0.048032697 | N8: =M8*(1-$C$11) -> 0.03998722
B9: Bull Case | C9: 0.15 | E9: =C9 -> 0.15 | F9: =E9 -> 0.15 | G9: =F9 -> 0.15 | H9: =G9 -> 0.15 | I9: =H9 -> 0.15 | J9: =I9*(1-$C$11) -> 0.124875 | K9: =J9*(1-$C$11) -> 0.10395844 | L9: =K9*(1-$C$11) -> 0.086545399 | M9: =L9*(1-$C$11) -> 0.072049045 | N9: =M9*(1-$C$11) -> 0.05998083
B10: Worst Case | C10: 0.05 | E10: =C10 -> 0.05 | F10: =E10 -> 0.05 | G10: =F10 -> 0.05 | H10: =G10 -> 0.05 | I10: =H10 -> 0.05 | J10: =I10*(1-$C$11) -> 0.041625 | K10: =J10*(1-$C$11) -> 0.034652813 | L10: =K10*(1-$C$11) -> 0.028848466 | M10: =L10*(1-$C$11) -> 0.024016348 | N10: =M10*(1-$C$11) -> 0.01999361
B11: Tapering | C11: 0.1675

Sheet Historical
B6: (Source:Annual Report) | E6: (Amounts in ₹MM unless otherwise stated)
B7: STATEMENT OF PROFIT & LOSS
B8: Particulars | D8: 44286 | E8: 44651 | F8: 45016 | G8: 45382 | H8: 45747
B9: Income
B10: Revenue from operations | D10: 334981.4 | E10: 386544.9 | F10: 438856.8 | G10: 484968.5 | H10: 525784.4
B11: Other income | D11: 8355.2 | E11: 9215.1 | F11: 6345.2 | G11: 13541.9 | H11: 19650.4
B12: Total Income | D12: =SUM(D10:D11) -> 343336.6 | E12: =SUM(E10:E11) -> 395760 | F12: =SUM(F10:F11) -> 445202 | G12: =SUM(G10:G11) -> 498510.4 | H12: =SUM(H10:H11) -> 545434.8
B13: Expenses
B14: Cost of materials consumed | D14: 61531.3 | E14: 70491.2 | F14: 77775.7 | G14: 69043.3 | H14: 64491
B15: Purchases of stock-in-trade | D15: 31751.7 | E15: 34100.3 | F15: 35715 | G15: 34661.5 | H15: 41479.5
B16: Changes in inventories | D16: -6382.2 | E16: -1076.1 | F16: -6869.1 | G16: 2921.3 | H16: 1503.1
B17: Employee benefits expense | D17: 68622.3 | E17: 73008.3 | F17: 82960.3 | G17: 94290.6 | H17: 99731.2
B18: Finance costs | D18: 1414.3 | E18: 1273.5 | F18: 1720 | G18: 2384.7 | H18: 2313.6
B19: Depreciation & amortisation | D19: 20799.5 | E19: 21437.4 | F19: 25294.3 | G19: 25566.4 | H19: 25753.9
B20: Other expenses | D20: 94781.1 | E20: 107583.6 | F20: 131546 | G20: 154181.8 | H20: 167718
B21: Net (gain)/loss on forex | D21: -236.5 | E21: -1539.6 | F21: 1261 | G21: -361.3 | H21: -1855.3
B22: Total Expenses | D22: =SUM(D14:D21) -> 272281.5 | E22: =SUM(E14:E21) -> 305278.6 | F22: =SUM(F14:F21) -> 349403.2 | G22: =SUM(G14:G21) -> 382688.3 | H22: =SUM(H14:H21) -> 401135
B23: Profit before exceptional items & tax | D23: =D12-D22 -> 71055.1 | E23: =E12-E22 -> 90481.4 | F23: =F12-F22 -> 95798.8 | G23: =G12-G22 -> 115822.1 | H23: =H12-H22 -> 144299.8
B24: Exceptional items | D24: 43061.4 | E24: 45668.2 | F24: 1714.5 | G24: 4943.2 | H24: 6778.5
B25: Profit before tax (PBT) | D25: =D23-D24 -> 27993.7 | E25: =E23-E24 -> 44813.2 | F25: =F23-F24 -> 94084.3 | G25: =G23-G24 -> 110878.9 | H25: =H23-H24 -> 137521.3
B26: Tax Expense
B27: Current tax | D27: 9573 | E27: 3543.9 | F27: 18692.2 | G27: 19893 | H27: 33200.5
B28: Deferred tax | D28: -331 | E28: 7975.3 | F28: -10216.3 | G28: -5498.5 | H28: -9255
B29: Deferred tax (exceptional) | D29: -4095.1 | E29: -764.2 | F29: - | G29: - | H29: 3774.8
B30: Total Tax Expense | D30: =SUM(D27:D29) -> 5146.9 | E30: =SUM(E27:E29) -> 10755 | F30: =SUM(F27:F29) -> 8475.9 | G30: =SUM(G27:G29) -> 14394.5 | H30: =SUM(H27:H29) -> 27720.3
B31: Share of (loss)/gain of associates or JV | D31: -123.3 | E31: -165.4 | F31: -479 | G31: -384.1 | H31: -153.5
B32: Profit for the year | D32: =D25-D30+D31 -> 22723.5 | E32: =E25-E30+E31 -> 33892.8 | F32: =F25-F30+F31 -> 85129.4 | G32: =G25-G30+G31 -> 96100.3 | H32: =H25-H30+H31 -> 109647.5
B34: BALANCE SHEET
B35: Particulars | D35: 44286 | E35: 44651 | F35: 45016 | G35: 45382 | H35: 45747
B36: ASSETS
B37: Non-current assets
B38: Property, plant and equipment | D38: 102349.9 | E38: 103713.8 | F38: 103903.8 | G38: 101923.2 | H38: 100359.4
B39: Capital work-in-progress | D39: 9365.2 | E39: 7975.1 | F39: 9633.5 | G39: 11077.3 | H39: 12343.4
B40: Goodwill (Net) | D40: 62876.4 | E40: 65494.5 | F40: 87127.1 | G40: 85689.9 | H40: 89394.2
B41: Other intangible assets | D41: 50303.5 | E41: 55389.1 | F41: 53170.3 | G41: 44868.4 | H41: 36109.2
B42: Intangible assets under development | D42: 6303.1 | E42: 4892.9 | F42: 40098.1 | G42: 42461.5 | H42: 54096.2
B43: Financial assets | D43: 65788.5 | E43: 53412.6 | F43: 56233.8 | G43: 65600.3 | H43: 48775.3
B44: Deferred tax assets (Net) | D44: 35564.4 | E44: 28967.2 | F44: 31642.4 | G44: 41036.5 | H44: 44075.5
B45: Income tax assets (Net) | D45: 34327.8 | E45: 25115.3 | F45: 23069.8 | G45: 22850.3 | H45: 4206.7
B46: Other non-current assets | D46: 5367.4 | E46: 2888.4 | F46: 3723.7 | G46: 4739.3 | H46: 5401.2
B47: Total non-current assets | D47: =SUM(D38:D46) -> 372246.2 | E47: =SUM(E38:E46) -> 347848.9 | F47: =SUM(F38:F46) -> 408602.5 | G47: =SUM(G38:G46) -> 420246.7 | H47: =SUM(H38:H46) -> 394761.1
B48: Current assets
B49: Inventories | D49: 89970.2 | E49: 89968.1 | F49: 105130.5 | G49: 98682.9 | H49: 102433.3
B50: – Investments | D50: 31300.6 | E50: 76339.4 | F50: 93726.1 | G50: 85845.4 | H50: 136561
B51: – Trade receivables | D51: 90614 | E51: 105928.9 | F51: 114385.1 | G51: 112493.7 | H51: 130461.1
B52: – Cash and cash equivalents | D52: 62730.3 | E52: 45082.5 | F52: 46237.3 | G52: 92856.5 | H52: 102687.7
B53: – Bank balances (other than above) | D53: 1724.8 | E53: 5251 | F53: 11465.6 | G53: 12350.3 | H53: 10628.5
B54: – Loans | D54: 560.1 | E54: 1699.7 | F54: 413.2 | G54: 650.2 | H54: 483.8
B55: – Other financial assets | D55: 8759.3 | E55: 7024.7 | F55: 7645.1 | G55: 9172 | H55: 17406.6
B56: Other current assets | D56: 18761.5 | E56: 18855.5 | F56: 19616.5 | G56: 22280.1 | H56: 25278.6
B57: Total current assets | D57: =SUM(D49:D56) -> 304420.8 | E57: =SUM(E49:E56) -> 350149.8 | F57: =SUM(F49:F56) -> 398619.4 | G57: =SUM(G49:G56) -> 434331.1 | H57: =SUM(H49:H56) -> 525940.6
B58: Assets classified as held for sale | D58: 0 | E58: 0 | F58: 214 | G58: 418.7 | H58: 304.1
B59: TOTAL ASSETS | D59: =D47+D57+D58 -> 676667 | E59: =E47+E57+E58 -> 697998.7 | F59: =F47+F57+F58 -> 807435.9 | G59: =G47+G57+G58 -> 854996.5 | H59: =H47+H57+H58 -> 921005.8
B60: EQUITY & LIABILITIES
B61: Equity
B62: Equity share capital | D62: 2399.3 | E62: 2399.3 | F62: 2399.3 | G62: 2399.3 | H62: 2399.3
B63: Reserves | D63: 462228.5 | E63: 477712.9 | F63: 557554.5 | G63: 634268.2 | H63: 719780.9
B64: Non-controlling interests | D64: 30170.5 | E64: 30548.9 | F64: 33200.9 | G64: 34591.9 | H64: 2679.3
B65: Total Equity | D65: =SUM(D62:D64) -> 494798.3 | E65: =SUM(E62:E64) -> 510661.1 | F65: =SUM(F62:F64) -> 593154.7 | G65: =SUM(G62:G64) -> 671259.4 | H65: =SUM(H62:H64) -> 724859.5
B66: Liabilities
B67: Non-current liabilities
B68: Borrowings | D68: 6547 | E68: 2299.2 | F68: 0 | G68: 13.3 | H68: 25.2
B69: Lease liabilities | D69: 2434 | E69: 2517.9 | F69: 5599.1 | G69: 3022.9 | H69: 3557.4
B70: Provisions | D70: 3271.2 | E70: 3690.7 | F70: 3429.1 | G70: 4138.9 | H70: 4650.4
B71: Deferred tax liabilities (Net) | D71: 445.1 | E71: 318.6 | F71: 316.9 | G71: 1718.6 | H71: 1924.4
B72: Other non-current liabilities | D72: 7715.1 | E72: 6505.7 | F72: 5866.1 | G72: 4999.4 | H72: 3959.2
B73: Non-current tax liabilities | D73: - | E73: - | F73: - | G73: - | H73: 87.6
B74: Total non-current liabilities | D74: =SUM(D68:D73) -> 20412.4 | E74: =SUM(E68:E73) -> 15332.1 | F74: =SUM(F68:F73) -> 15211.2 | G74: =SUM(G68:G73) -> 13893.1 | H74: =SUM(H68:H73) -> 14204.2
B75: Current liabilities
B76: Borrowings | D76: 28687.8 | E76: 7007.7 | F76: 61978.8 | G76: 28443.6 | H76: 18671.1
B77: Lease liabilities | D77: 1016.7 | E77: 1078.2 | F77: 1280.8 | G77: 1256.9 | H77: 1368.2
B78: Trade payables | D78: 39736.6 | E78: 44793.4 | F78: 56815.2 | G78: 56533 | H78: 61843.4
B79: Other current liabilities | D79: 44397.9 | E79: 25866.6 | F79: 22358.1 | G79: 25911.6 | H79: 31176.3
B80: Provisions | D80: 45826.5 | E80: 91478.2 | F80: 53543.8 | G80: 53575.6 | H80: 61551.3
B81: Current tax liabilities | D81: 1790.8 | E81: 1781.4 | F81: 3087.1 | G81: 4117 | H81: 7331.8
B82: Total current liabilities | D82: =SUM(D76:D81) -> 161456.3 | E82: =SUM(E76:E81) -> 172005.5 | F82: =SUM(F76:F81) -> 199063.8 | G82: =SUM(G76:G81) -> 169837.7 | H82: =SUM(H76:H81) -> 181942.1
B83: Liabilities linked to held-for-sale assets | D83: 0 | E83: 0 | F83: 6.2 | G83: 6.3 | H83: 0
B84: Total Liabilities | D84: =D74+D82+D83 -> 181868.7 | E84: =E74+E82+E83 -> 187337.6 | F84: =F74+F82+F83 -> 214281.2 | G84: =G74+G82+G83 -> 183737.1 | H84: =H74+H82+H83 -> 196146.3
B86: TOTAL EQUITY & LIABILITIES | D86: =D65+D84 -> 676667 | E86: =E65+E84 -> 697998.7 | F86: =F65+F84 -> 807435.9 | G86: =G65+G84 -> 854996.5 | H86: =H65+H84 -> 921005.8
D87: =IF(D86=D59,"Tallied","Error") -> Tallied | E87: =IF(E86=E59,"Tallied","Error") -> Tallied | F87: =IF(F86=F59,"Tallied","Error") -> Tallied | G87: =IF(G86=G59,"Tallied","Error") -> Tallied | H87: =IF(H86=H59,"Tallied","Error") -> Tallied
B89: CASH FLOW STATEMENT
B90: Particulars
B91: A. Cash Flow from Operating Activities
B92: Profit before tax | D92: 27993.7 | E92: 44813.2 | F92: 94084.3 | G92: 110878.9 | H92: 137521.3
B93: Depreciation & amortisation | D93: 20799.5 | E93: 21437.4 | F93: 25294.3 | G93: 25566.4 | H93: 25753.9
B94: Finance costs | D94: 1414.3 | E94: 1273.5 | F94: 1720 | G94: 2384.7 | H94: 2313.6
B95: Interest & dividend income (net) | D95: -4671.7 | E95: -7687 | F95: -5309.9 | G95: -11262.1 | H95: -12970.3
B96: Other adjustments (net) | D96: 556.4 | E96: 4725.6 | F96: 5521.2 | G96: -1145 | H96: -3893.6
B97: Operating profit before WC changes | D97: =SUM(D92:D96) -> 46092.2 | E97: =SUM(E92:E96) -> 64562.7 | F97: =SUM(F92:F96) -> 121309.9 | G97: =SUM(G92:G96) -> 126422.9 | H97: =SUM(H92:H96) -> 148724.9
B98: Working Capital Changes
B99: Inventories | D99: -10802.9 | E99: 3069.5 | F99: -12022 | G99: 5988.1 | H99: -1839.7
B100: Trade receivables | D100: 937.3 | E100: -13422.6 | F100: -9531.7 | G100: 3528.9 | H100: -16020.5
B101: Other assets | D101: 1166.2 | E101: 141.1 | F101: -2158.1 | G101: -3839 | H101: -593.2
B102: Trade payables | D102: 3814.6 | E102: 3699.2 | F102: 11823.7 | G102: 2497.2 | H102: 5279.7
B103: Other liabilities | D103: 24983.5 | E103: -23333.5 | F103: -6691.5 | G103: 2409.2 | H103: 1820.3
B104: Provisions | D104: 5542.2 | E104: 45436.8 | F104: -38038.6 | G104: 36.9 | H104: 8117.8
B105: Cash from operations | D105: =SUM(D97:D104) -> 71733.1 | E105: =SUM(E97:E104) -> 80153.2 | F105: =SUM(F97:F104) -> 64691.7 | G105: =SUM(G97:G104) -> 137044.2 | H105: =SUM(H97:H104) -> 145489.3
B106: Tax paid (net) | D106: -10029.4 | E106: 9692.2 | F106: -15098.4 | G106: -15694.4 | H106: -4768.4
B107: Net Cash from Operating (A) | D107: =D105+D106 -> 61703.7 | E107: =E105+E106 -> 89845.4 | F107: =F105+F106 -> 49593.3 | G107: =G105+G106 -> 121349.8 | H107: =H105+H106 -> 140720.9
B108: B. Cash Flow from Investing Activities
...

Sheet Schedules
N6: (Amounts in ₹MM unless otherwise stated)
B7: SUPPORTING SCHEDULES
C8: Historical | H8: Forecasting
B9: Particulars | C9: 44286 | D9: 44651 | E9: 45016 | F9: 45382 | G9: 45747 | H9: 46112 | I9: 46477 | J9: 46843 | K9: 47208 | L9: 47573 | M9: =L9+365 -> 47938 | N9: =M9+365 -> 48303 | O9: =N9+365 -> 48668 | P9: =O9+365 -> 49033 | Q9: =P9+365 -> 49398
B10: Change in Working Capital
B11: Trade Receivables | C11: =CFS!D17 -> 937.3 | D11: =CFS!E17 -> -13422.6 | E11: =CFS!F17 -> -9531.7 | F11: =CFS!G17 -> 3528.9 | G11: =CFS!H17 -> -16020.5 | H11: ='Balance Sheet'!H20-'Balance Sheet'!I20 -> -18210.041 | I11: ='Balance Sheet'!I20-'Balance Sheet'!J20 -> -14867.114 | J11: ='Balance Sheet'!J20-'Balance Sheet'!K20 -> -16353.826 | K11: ='Balance Sheet'!K20-'Balance Sheet'!L20 -> -17989.208 | L11: ='Balance Sheet'!L20-'Balance Sheet'!M20 -> -19788.129 | M11: ='Balance Sheet'!M20-'Balance Sheet'!N20 -> -18120.979 | N11: ='Balance Sheet'!N20-'Balance Sheet'!O20 -> -16341.601 | O11: ='Balance Sheet'!O20-'Balance Sheet'!P20 -> -14547.243 | ... Q11: ='Balance Sheet'!Q20-'Balance Sheet'!R20 -> -11175.971
B12: Inventories | C12: =CFS!D16 -> -10802.9 | D12: =CFS!E16 -> 3069.5 | E12: =CFS!F16 -> -12022 | F12: =CFS!G16 -> 5988.1 | G12: =CFS!H16 -> -1839.7 | H12: ='Balance Sheet'!H18-'Balance Sheet'!I18 -> -29349.118 | I12: ='Balance Sheet'!I18-'Balance Sheet'!J18 -> -13178.242 | J12: ='Balance Sheet'!J18-'Balance Sheet'!K18 -> -14496.066 | K12: ='Balance Sheet'!K18-'Balance Sheet'!L18 -> -15945.673 | L12: ='Balance Sheet'!L18-'Balance Sheet'!M18 -> -17540.24 | M12: ='Balance Sheet'!M18-'Balance Sheet'!N18 -> -16062.475 | N12: ='Balance Sheet'!N18-'Balance Sheet'!O18 -> -14485.23 | O12: ='Balance Sheet'!O18-'Balance Sheet'!P18 -> -12894.707 | ... Q12: ='Balance Sheet'!Q18-'Balance Sheet'!R18 -> -9906.4044
B13: Trade Payables | C13: =CFS!D19 -> 3814.6 | D13: =CFS!E19 -> 3699.2 | E13: =CFS!F19 -> 11823.7 | F13: =CFS!G19 -> 2497.2 | G13: =CFS!H19 -> 5279.7 | H13: ='Balance Sheet'!I48-'Balance Sheet'!H48 -> 8025.4336 | I13: ='Balance Sheet'!J48-'Balance Sheet'!I48 -> 6986.8834 | J13: ='Balance Sheet'!K48-'Balance Sheet'!J48 -> 7685.5717 | K13: ='Balance Sheet'!L48-'Balance Sheet'!K48 -> 8454.1289 | L13: ='Balance Sheet'!M48-'Balance Sheet'!L48 -> 9299.5418 | M13: ='Balance Sheet'!N48-'Balance Sheet'!M48 -> 8516.0554 | N13: ='Balance Sheet'!O48-'Balance Sheet'!N48 -> 7679.8266 | O13: ='Balance Sheet'!P48-'Balance Sheet'!O48 -> 6836.5581 | ... Q13: ='Balance Sheet'!R48-'Balance Sheet'!Q48 -> 5252.2099
B14: Others | C14: =CFS!D18+CFS!D20+CFS!D21 -> 31691.9 | D14: =CFS!E18+CFS!E20+CFS!E21 -> 22244.4 | E14: =CFS!F18+CFS!F20+CFS!F21 -> -46888.2 | F14: =CFS!G18+CFS!G20+CFS!G21 -> -1392.9 | G14: =CFS!H18+CFS!H20+CFS!H21 -> 9344.9 | H14: 0 | I14: 0 | J14: 0 | K14: 0 | L14: 0 | M14: 0 | N14: 0 | O14: 0 | P14: 0 | Q14: 0
B15: Total | C15: =SUM(C11:C14) -> 25640.9 | D15: =SUM(D11:D14) -> 15590.5 | E15: =SUM(E11:E14) -> -56618.2 | F15: =SUM(F11:F14) -> 10621.3 | G15: =SUM(G11:G14) -> -3235.6 | H15: =SUM(H11:H14) -> -39533.726 | I15: =SUM(I11:I14) -> -21058.473 | J15: =SUM(J11:J14) -> -23164.32 | ... Q15: =SUM(Q11:Q14) -> -15830.165
B17: Depreciation
B18: PPE Opening | C18: =C21+C20 -> 123149.4 | D18: =C21 -> 102349.9 | E18: =D21 -> 103713.8 | F18: =E21 -> 103903.8 | G18: =F21 -> 101923.2 | H18: =G21 -> 100359.4 | I18: =H21 -> 98762.428 | J18: =I21 -> 97693.089 | K18: =J21 -> 96768.011 | ... Q18: =P21 -> 94581.018
B19: Add: Capex | C19: 0 | D19: =D21-D18+D20 -> 22801.3 | E19: =E21-E18+E20 -> 25484.3 | F19: =F21-F18+F20 -> 23585.8 | G19: =G21-G18+G20 -> 24190.1 | H19: =AVERAGE(D19:G19) -> 24015.375 | I19: =H19*(1+0.005) -> 24135.452 | J19: =I19*(1+0.005) -> 24256.129 | K19: =J19*(1+0.005) -> 24377.41 | L19: =K19*(1+0.005) -> 24499.297 | M19: =L19*(1+0.005) -> 24621.793 | N19: =M19*(1+0.005) -> 24744.902 | O19: =N19*(1+0.005) -> 24868.627 | P19: =O19*(1+0.005) -> 24992.97 | Q19: =P19*(1+0.005) -> 25117.935
B20: Less: Depreciation | C20: ='Income Statement'!C15 -> 20799.5 | D20: ='Income Statement'!D15 -> 21437.4 | E20: ='Income Statement'!E15 -> 25294.3 | F20: ='Income Statement'!F15 -> 25566.4 | G20: ='Income Statement'!G15 -> 25753.9 | H20: =H18*Assumptions!H14 -> 25612.347 | I20: =I18*Assumptions!I14 -> 25204.79 | J20: =J18*Assumptions!J14 -> 25181.207 | K20: =K18*Assumptions!K14 -> 24942.761 | L20: =L18*Assumptions!L14 -> 25045.007 | M20: =M18*Assumptions!M14 -> 24902.939 | N20: =N18*Assumptions!N14 -> 25078.044 | O20: =O18*Assumptions!O14 -> 24990.448 | ... Q20: =Q18*Assumptions!Q14 -> 25242.1
B21: PPE Closing | C21: ='Balance Sheet'!D11 -> 102349.9 | D21: ='Balance Sheet'!E11 -> 103713.8 | E21: ='Balance Sheet'!F11 -> 103903.8 | F21: ='Balance Sheet'!G11 -> 101923.2 | G21: ='Balance Sheet'!H11 -> 100359.4 | H21: =H18+H19-H20 -> 98762.428 | I21: =I18+I19-I20 -> 97693.089 | J21: =J18+J19-J20 -> 96768.011 | K21: =K18+K19-K20 -> 96202.661 | L21: =L18+L19-L20 -> 95656.95 | M21: =M18+M19-M20 -> 95375.804 | N21: =N18+N19-N20 -> 95042.663 | O21: =O18+O19-O20 -> 94920.841 | ... Q21: =Q18+Q19-Q20 -> 94456.853
B23: Debt & Interest Schedule
B24: Opening | C24: 33430.4 | D24: =C26 -> 35234.8 | E24: =D26 -> 9306.9 | F24: =E26 -> 61978.8 | G24: =F26 -> 28456.9 | H24: =G26 -> 18696.3 | I24: =H26 -> 18696.3 | J24: =I26 -> 18696.3 | K24: =J26 -> 18696.3 | ... Q24: =P26 -> 18696.3
B25: Issuance (repayment) | C25: =C26-C24 -> 1804.4 | D25: =D26-D24 -> -25927.9 | E25: =E26-E24 -> 52671.9 | F25: =F26-F24 -> -33521.9 | G25: =G26-G24 -> -9760.6 | H25: 0 | I25: 0 | J25: 0 | K25: 0 | L25: 0 | M25: 0 | N25: 0 | O25: 0 | P25: 0 | Q25: 0
B26: Closing | C26: ='Balance Sheet'!D38+'Balance Sheet'!D46 -> 35234.8 | D26: ='Balance Sheet'!E38+'Balance Sheet'!E46 -> 9306.9 | E26: ='Balance Sheet'!F38+'Balance Sheet'!F46 -> 61978.8 | F26: ='Balance Sheet'!G38+'Balance Sheet'!G46 -> 28456.9 | G26: ='Balance Sheet'!H38+'Balance Sheet'!H46 -> 18696.3 | H26: =H24+H25 -> 18696.3 | I26: =I24+I25 -> 18696.3 | J26: =J24+J25 -> 18696.3 | K26: =K24+K25 -> 18696.3 | L26: =L24+L25 -> 18696.3 | M26: =M24+M25 -> 18696.3 | N26: =N24+N25 -> 18696.3 | O26: =O24+O25 -> 18696.3 | ... Q26: =Q24+Q25 -> 18696.3
B27: Interest Expenses | C27: ='Income Statement'!C17 -> 1414.3 | D27: ='Income Statement'!D17 -> 1273.5 | E27: ='Income Statement'!E17 -> 1720 | F27: ='Income Statement'!F17 -> 2384.7 | G27: ='Income Statement'!G17 -> 2313.6 | H27: =H24*Assumptions!H15 -> 1520.0447 | I27: =I24*Assumptions!I15 -> 1520.0447 | J27: =J24*Assumptions!J15 -> 1520.0447 | K27: =K24*Assumptions!K15 -> 1520.0447 | L27: =L24*Assumptions!L15 -> 1520.0447 | M27: =M24*Assumptions!M15 -> 1520.0447 | N27: =N24*Assumptions!N15 -> 1520.0447 | O27: =O24*Assumptions!O15 -> 1520.0447 | ... Q27: =Q24*Assumptions!Q15 -> 1520.0447

Sheet Balance Sheet
O6: (Amounts in ₹MM unless otherwise stated)
D7: Historical | I7: Forecasting
B8: Particulars | D8: 44286 | E8: 44651 | F8: 45016 | G8: 45382 | H8: 45747 | I8: 46112 | J8: 46477 | K8: 46843 | L8: 47208 | M8: 47573 | N8: =M8+365 -> 47938 | O8: =N8+365 -> 48303 | P8: =O8+365 -> 48668 | Q8: =P8+365 -> 49033 | R8: =Q8+365 -> 49398
B9: ASSETS
B10: Non-current assets
B11: Property, plant and equipment | D11: =Historical!D38 -> 102349.9 | E11: =Historical!E38 -> 103713.8 | F11: =Historical!F38 -> 103903.8 | G11: =Historical!G38 -> 101923.2 | H11: =Historical!H38 -> 100359.4 | I11: =Schedules!H21 -> 98762.428 | J11: =Schedules!I21 -> 97693.089 | K11: =Schedules!J21 -> 96768.011 | L11: =Schedules!K21 -> 96202.661 | M11: =Schedules!L21 -> 95656.95 | N11: =Schedules!M21 -> 95375.804 | O11: =Schedules!N21 -> 95042.663 | P11: =Schedules!O21 -> 94920.841 | ... R11: =Schedules!Q21 -> 94456.853
B12: Capital work-in-progress | D12: =Historical!D39 -> 9365.2 | E12: =Historical!E39 -> 7975.1 | F12: =Historical!F39 -> 9633.5 | G12: =Historical!G39 -> 11077.3 | H12: =Historical!H39 -> 12343.4 | I12: =H12 -> 12343.4 | J12: =I12 -> 12343.4 | K12: =J12 -> 12343.4 | L12: =K12 -> 12343.4 | M12: =L12 -> 12343.4 | N12: =M12 -> 12343.4 | O12: =N12 -> 12343.4 | P12: =O12 -> 12343.4 | ... R12: =Q12 -> 12343.4
B13: Goodwill (Net) | D13: =Historical!D40 -> 62876.4 | E13: =Historical!E40 -> 65494.5 | F13: =Historical!F40 -> 87127.1 | G13: =Historical!G40 -> 85689.9 | H13: =Historical!H40 -> 89394.2 | I13: =H13 -> 89394.2 | J13: =I13 -> 89394.2 | K13: =J13 -> 89394.2 | L13: =K13 -> 89394.2 | M13: =L13 -> 89394.2 | N13: =M13 -> 89394.2 | O13: =N13 -> 89394.2 | P13: =O13 -> 89394.2 | ... R13: =Q13 -> 89394.2
B14: Financial assets | D14: =Historical!D43 -> 65788.5 | E14: =Historical!E43 -> 53412.6 | F14: =Historical!F43 -> 56233.8 | G14: =Historical!G43 -> 65600.3 | H14: =Historical!H43 -> 48775.3 | I14: =H14 -> 48775.3 | J14: =I14 -> 48775.3 | K14: =J14 -> 48775.3 | L14: =K14 -> 48775.3 | M14: =L14 -> 48775.3 | N14: =M14 -> 48775.3 | O14: =N14 -> 48775.3 | P14: =O14 -> 48775.3 | ... R14: =Q14 -> 48775.3
B15: Other non-current assets | D15: =Historical!D41+Historical!D42+Historical!D44+Historical!D45+Historical!D46 -> 131866.2 | E15: =Historical!E41+Historical!E42+Historical!E44+Historical!E45+Historical!E46 -> 117252.9 | F15: =Historical!F41+Historical!F42+Historical!F44+Historical!F45+Historical!F46 -> 151704.3 | G15: =Historical!G41+Historical!G42+Historical!G44+Historical!G45+Historical!G46 -> 155956 | H15: =Historical!H41+Historical!H42+Historical!H44+Historical!H45+Historical!H46 -> 143888.8 | I15: =H15 -> 143888.8 | J15: =I15 -> 143888.8 | K15: =J15 -> 143888.8 | L15: =K15 -> 143888.8 | M15: =L15 -> 143888.8 | N15: =M15 -> 143888.8 | O15: =N15 -> 143888.8 | P15: =O15 -> 143888.8 | ... R15: =Q15 -> 143888.8
B16: Total non-current assets | D16: =SUM(D11:D15) -> 372246.2 | E16: =SUM(E11:E15) -> 347848.9 | F16: =SUM(F11:F15) -> 408602.5 | G16: =SUM(G11:G15) -> 420246.7 | H16: =SUM(H11:H15) -> 394761.1 | I16: =SUM(I11:I15) -> 393164.13 | J16: =SUM(J11:J15) -> 392094.79 | K16: =SUM(K11:K15) -> 391169.71 | ... R16: =SUM(R11:R15) -> 388858.55
B17: Current assets
B18: Inventories | D18: =Historical!D49 -> 89970.2 | E18: =Historical!E49 -> 89968.1 | F18: =Historical!F49 -> 105130.5 | G18: =Historical!G49 -> 98682.9 | H18: =Historical!H49 -> 102433.3 | I18: =('Income Statement'!H10*Assumptions!H20)/365 -> 131782.42 | J18: =('Income Statement'!I10*Assumptions!I20)/365 -> 144960.66 | K18: =('Income Statement'!J10*Assumptions!J20)/365 -> 159456.73 | L18: =('Income Statement'!K10*Assumptions!K20)/365 -> 175402.4 | M18: =('Income Statement'!L10*Assumptions!L20)/365 -> 192942.64 | N18: =('Income Statement'!M10*Assumptions!M20)/365 -> 209005.11 | O18: =('Income Statement'!N10*Assumptions!N20)/365 -> 223490.34 | P18: =('Income Statement'!O10*Assumptions!O20)/365 -> 236385.05 | ... R18: =('Income Statement'!Q10*Assumptions!Q20)/365 -> 257645.67
B19: Investments | D19: =Historical!D50 -> 31300.6 | E19: =Historical!E50 -> 76339.4 | F19: =Historical!F50 -> 93726.1 | G19: =Historical!G50 -> 85845.4 | H19: =Historical!H50 -> 136561 | I19: =H19 -> 136561 | J19: =I19 -> 136561 | K19: =J19 -> 136561 | L19: =K19 -> 136561 | M19: =L19 -> 136561 | N19: =M19 -> 136561 | O19: =N19 -> 136561 | P19: =O19 -> 136561 | ... R19: =Q19 -> 136561
B20: Trade receivables | D20: =Historical!D51 -> 90614 | E20: =Historical!E51 -> 105928.9 | F20: =Historical!F51 -> 114385.1 | G20: =Historical!G51 -> 112493.7 | H20: =Historical!H51 -> 130461.1 | I20: =('Income Statement'!H9*Assumptions!H21)/365 -> 148671.14 | J20: =('Income Statement'!I9*Assumptions!I21)/365 -> 163538.26 | K20: =('Income Statement'!J9*Assumptions!J21)/365 -> 179892.08 | L20: =('Income Statement'!K9*Assumptions!K21)/365 -> 197881.29 | M20: =('Income Statement'!L9*Assumptions!L21)/365 -> 217669.42 | N20: =('Income Statement'!M9*Assumptions!M21)/365 -> 235790.4 | O20: =('Income Statement'!N9*Assumptions!N21)/365 -> 252132 | P20: =('Income Statement'!O9*Assumptions!O21)/365 -> 266679.24 | ... R20: =('Income Statement'!Q9*Assumptions!Q21)/365 -> 290664.53
B21: Cash and cash equivalents | D21: =Historical!D52 -> 62730.3 | E21: =Historical!E52 -> 45082.5 | F21: =Historical!F52 -> 46237.3 | G21: =Historical!G52 -> 92856.5 | H21: =Historical!H52 -> 102687.7 | I21: =CFS!I45 -> 140651.23 | J21: =CFS!J45 -> 205869.13 | K21: =CFS!K45 -> 278596.68 | L21: =CFS!L45 -> 359740.75 | M21: =CFS!M45 -> 450012.52 | N21: =CFS!N45 -> 553472.37 | O21: =CFS!O45 -> 668976.23 | P21: =CFS!P45 -> 795676.4 | ... R21: =CFS!R45 -> 1077671.7
B22: Bank balances (other than above) | D22: =Historical!D53 -> 1724.8 | E22: =Historical!E53 -> 5251 | F22: =Historical!F53 -> 11465.6 | G22: =Historical!G53 -> 12350.3 | H22: =Historical!H53 -> 10628.5 | I22: =H22 -> 10628.5 | J22: =I22 -> 10628.5 | K22: =J22 -> 10628.5 | L22: =K22 -> 10628.5 | M22: =L22 -> 10628.5 | N22: =M22 -> 10628.5 | O22: =N22 -> 10628.5 | P22: =O22 -> 10628.5 | ... R22: =Q22 -> 10628.5
B23: Loans & Advances | D23: =Historical!D54 -> 560.1 | E23: =Historical!E54 -> 1699.7 | F23: =Historical!F54 -> 413.2 | G23: =Historical!G54 -> 650.2 | H23: =Historical!H54 -> 483.8 | I23: =H23 -> 483.8 | J23: =I23 -> 483.8 | K23: =J23 -> 483.8 | L23: =K23 -> 483.8 | M23: =L23 -> 483.8 | N23: =M23 -> 483.8 | O23: =N23 -> 483.8 | P23: =O23 -> 483.8 | ... R23: =Q23 -> 483.8
B24: Other financial assets | D24: =Historical!D55 -> 8759.3 | E24: =Historical!E55 -> 7024.7 | F24: =Historical!F55 -> 7645.1 | G24: =Historical!G55 -> 9172 | H24: =Historical!H55 -> 17406.6 | I24: =H24 -> 17406.6 | J24: =I24 -> 17406.6 | K24: =J24 -> 17406.6 | L24: =K24 -> 17406.6 | M24: =L24 -> 17406.6 | N24: =M24 -> 17406.6 | O24: =N24 -> 17406.6 | P24: =O24 -> 17406.6 | ... R24: =Q24 -> 17406.6
B25: Other current assets | D25: =Historical!D56 -> 18761.5 | E25: =Historical!E56 -> 18855.5 | F25: =Historical!F56 -> 19616.5 | G25: =Historical!G56 -> 22280.1 | H25: =Historical!H56 -> 25278.6 | I25: =H25 -> 25278.6 | J25: =I25 -> 25278.6 | K25: =J25 -> 25278.6 | L25: =K25 -> 25278.6 | M25: =L25 -> 25278.6 | N25: =M25 -> 25278.6 | O25: =N25 -> 25278.6 | P25: =O25 -> 25278.6 | ... R25: =Q25 -> 25278.6
B26: Total current assets | D26: =SUM(D18:D25) -> 304420.8 | E26: =SUM(E18:E25) -> 350149.8 | F26: =SUM(F18:F25) -> 398619.4 | G26: =SUM(G18:G25) -> 434331.1 | H26: =SUM(H18:H25) -> 525940.6 | I26: =SUM(I18:I25) -> 611463.29 | J26: =SUM(J18:J25) -> 704726.54 | K26: =SUM(K18:K25) -> 808303.99 | ... R26: =SUM(R18:R25) -> 1816340.4
B27: Assets classified as held for sale | D27: =Historical!D58 -> 0 | E27: =Historical!E58 -> 0 | F27: =Historical!F58 -> 214 | G27: =Historical!G58 -> 418.7 | H27: =Historical!H58 -> 304.1 | I27: =H27-0.1 -> 304 | J27: =I27 -> 304 | K27: =J27 -> 304 | L27: =K27 -> 304 | M27: =L27 -> 304 | N27: =M27 -> 304 | O27: =N27 -> 304 | P27: =O27 -> 304 | Q27: =P27 -> 304 | R27: =Q27 -> 304
B28: TOTAL ASSETS | D28: =D26+D16+D27 -> 676667 | E28: =E26+E16+E27 -> 697998.7 | F28: =F26+F16+F27 -> 807435.9 | G28: =G26+G16+G27 -> 854996.5 | H28: =H26+H16+H27 -> 921005.8 | I28: =I26+I16+I27 -> 1004931.4 | J28: =J26+J16+J27 -> 1097125.3 | K28: =K26+K16+K27 -> 1199777.7 | ... R28: =R26+R16+R27 -> 2205503
B30: EQUITY & LIABILITIES
B31: Equity
B32: Equity share capital | D32: =Historical!D62 -> 2399.3 | E32: =Historical!E62 -> 2399.3 | F32: =Historical!F62 -> 2399.3 | G32: =Historical!G62 -> 2399.3 | H32: =Historical!H62 -> 2399.3 | I32: =H32 -> 2399.3 | J32: =I32 -> 2399.3 | K32: =J32 -> 2399.3 | L32: =K32 -> 2399.3 | M32: =L32 -> 2399.3 | N32: =M32 -> 2399.3 | O32: =N32 -> 2399.3 | P32: =O32 -> 2399.3 | ... R32: =Q32 -> 2399.3
B33: Reserves | D33: =Historical!D63 -> 462228.5 | E33: =Historical!E63 -> 477712.9 | F33: =Historical!F63 -> 557554.5 | G33: =Historical!G63 -> 634268.2 | H33: =Historical!H63 -> 719780.9 | I33: =H33+('Income Statement'!H22*(1-Assumptions!H16)) -> 795681.08 | J33: =I33+('Income Statement'!I22*(1-Assumptions!I16)) -> 880888.12 | K33: =J33+('Income Statement'!J22*(1-Assumptions!J16)) -> 975854.91 | L33: =K33+('Income Statement'!K22*(1-Assumptions!K16)) -> 1081914.4 | M33: =L33+('Income Statement'!L22*(1-Assumptions!L16)) -> 1199669.3 | N33: =M33+('Income Statement'!M22*(1-Assumptions!M16)) -> 1328515.4 | O33: =N33+('Income Statement'!N22*(1-Assumptions!N16)) -> 1466833.1 | P33: =O33+('Income Statement'!O22*(1-Assumptions!O16)) -> 1614016.8 | ... R33: =Q33+('Income Statement'!Q22*(1-Assumptions!Q16)) -> 1929522
B34: Non-controlling interests | D34: =Historical!D64 -> 30170.5 | E34: =Historical!E64 -> 30548.9 | F34: =Historical!F64 -> 33200.9 | G34: =Historical!G64 -> 34591.9 | H34: =Historical!H64 -> 2679.3 | I34: =H34 -> 2679.3 | J34: =I34 -> 2679.3 | K34: =J34 -> 2679.3 | L34: =K34 -> 2679.3 | M34: =L34 -> 2679.3 | N34: =M34 -> 2679.3 | O34: =N34 -> 2679.3 | P34: =O34 -> 2679.3 | ... R34: =Q34 -> 2679.3
B35: Total Equity | D35: =SUM(D32:D34) -> 494798.3 | E35: =SUM(E32:E34) -> 510661.1 | F35: =SUM(F32:F34) -> 593154.7 | G35: =SUM(G32:G34) -> 671259.4 | H35: =SUM(H32:H34) -> 724859.5 | I35: =SUM(I32:I34) -> 800759.68 | J35: =SUM(J32:J34) -> 885966.72 | K35: =SUM(K32:K34) -> 980933.51 | ... R35: =SUM(R32:R34) -> 1934600.6
B36: Liabilities
B37: Non-current liabilities
B38: Borrowings | D38: =Historical!D68 -> 6547 | E38: =Historical!E68 -> 2299.2 | F38: =Historical!F68 -> 0 | G38: =Historical!G68 -> 13.3 | H38: =Historical!H68 -> 25.2 | I38: =H38 -> 25.2 | J38: =I38 -> 25.2 | K38: =J38 -> 25.2 | L38: =K38 -> 25.2 | M38: =L38 -> 25.2 | N38: =M38 -> 25.2 | O38: =N38 -> 25.2 | P38: =O38 -> 25.2 | ... R38: =Q38 -> 25.2
B39: Lease liabilities | D39: =Historical!D69 -> 2434 | E39: =Historical!E69 -> 2517.9 | F39: =Historical!F69 -> 5599.1 | G39: =Historical!G69 -> 3022.9 | H39: =Historical!H69 -> 3557.4 | I39: =H39 -> 3557.4 | J39: =I39 -> 3557.4 | K39: =J39 -> 3557.4 | L39: =K39 -> 3557.4 | M39: =L39 -> 3557.4 | N39: =M39 -> 3557.4 | O39: =N39 -> 3557.4 | P39: =O39 -> 3557.4 | ... R39: =Q39 -> 3557.4
B40: Provisions | D40: =Historical!D70 -> 3271.2 | E40: =Historical!E70 -> 3690.7 | F40: =Historical!F70 -> 3429.1 | G40: =Historical!G70 -> 4138.9 | H40: =Historical!H70 -> 4650.4 | I40: =H40 -> 4650.4 | J40: =I40 -> 4650.4 | K40: =J40 -> 4650.4 | L40: =K40 -> 4650.4 | M40: =L40 -> 4650.4 | N40: =M40 -> 4650.4 | O40: =N40 -> 4650.4 | P40: =O40 -> 4650.4 | ... R40: =Q40 -> 4650.4
B41: Deferred tax liabilities (Net) | D41: =Historical!D71 -> 445.1 | E41: =Historical!E71 -> 318.6 | F41: =Historical!F71 -> 316.9 | G41: =Historical!G71 -> 1718.6 | H41: =Historical!H71 -> 1924.4 | I41: =H41 -> 1924.4 | J41: =I41 -> 1924.4 | K41: =J41 -> 1924.4 | L41: =K41 -> 1924.4 | M41: =L41 -> 1924.4 | N41: =M41 -> 1924.4 | O41: =N41 -> 1924.4 | P41: =O41 -> 1924.4 | ... R41: =Q41 -> 1924.4
B42: Other non-current liabilities | D42: =Historical!D72 -> 7715.1 | E42: =Historical!E72 -> 6505.7 | F42: =Historical!F72 -> 5866.1 | G42: =Historical!G72 -> 4999.4 | H42: =Historical!H72 -> 3959.2 | I42: =H42 -> 3959.2 | J42: =I42 -> 3959.2 | K42: =J42 -> 3959.2 | L42: =K42 -> 3959.2 | M42: =L42 -> 3959.2 | N42: =M42 -> 3959.2 | O42: =N42 -> 3959.2 | P42: =O42 -> 3959.2 | ... R42: =Q42 -> 3959.2
B43: Non-current tax liabilities | D43: =Historical!D73 -> - | E43: =Historical!E73 -> - | F43: =Historical!F73 -> - | G43: =Historical!G73 -> - | H43: =Historical!H73 -> 87.6 | I43: =H43 -> 87.6 | J43: =I43 -> 87.6 | K43: =J43 -> 87.6 | L43: =K43 -> 87.6 | M43: =L43 -> 87.6 | N43: =M43 -> 87.6 | O43: =N43 -> 87.6 | P43: =O43 -> 87.6 | ... R43: =Q43 -> 87.6
B44: Total non-current liabilities | D44: =SUM(D38:D43) -> 20412.4 | E44: =SUM(E38:E43) -> 15332.1 | F44: =SUM(F38:F43) -> 15211.2 | G44: =SUM(G38:G43) -> 13893.1 | H44: =SUM(H38:H43) -> 14204.2 | I44: =SUM(I38:I43) -> 14204.2 | J44: =SUM(J38:J43) -> 14204.2 | K44: =SUM(K38:K43) -> 14204.2 | ... R44: =SUM(R38:R43) -> 14204.2
B45: Current liabilities
B46: Borrowings | D46: =Historical!D76 -> 28687.8 | E46: =Historical!E76 -> 7007.7 | F46: =Historical!F76 -> 61978.8 | G46: =Historical!G76 -> 28443.6 | H46: =Historical!H76 -> 18671.1 | I46: =H46 -> 18671.1 | J46: =I46 -> 18671.1 | K46: =J46 -> 18671.1 | L46: =K46 -> 18671.1 | M46: =L46 -> 18671.1 | N46: =M46 -> 18671.1 | O46: =N46 -> 18671.1 | P46: =O46 -> 18671.1 | ... R46: =Q46 -> 18671.1
B47: Lease liabilities | D47: =Historical!D77 -> 1016.7 | E47: =Historical!E77 -> 1078.2 | F47: =Historical!F77 -> 1280.8 | G47: =Historical!G77 -> 1256.9 | H47: =Historical!H77 -> 1368.2 | I47: =H47 -> 1368.2 | J47: =I47 -> 1368.2 | K47: =J47 -> 1368.2 | L47: =K47 -> 1368.2 | M47: =L47 -> 1368.2 | N47: =M47 -> 1368.2 | O47: =N47 -> 1368.2 | P47: =O47 -> 1368.2 | ... R47: =Q47 -> 1368.2
B48: Trade payables | D48: =Historical!D78 -> 39736.6 | E48: =Historical!E78 -> 44793.4 | F48: =Historical!F78 -> 56815.2 | G48: =Historical!G78 -> 56533 | H48: =Historical!H78 -> 61843.4 | I48: =('Income Statement'!H10*Assumptions!H22)/365 -> 69868.834 | J48: =('Income Statement'!I10*Assumptions!I22)/365 -> 76855.717 | K48: =('Income Statement'!J10*Assumptions!J22)/365 -> 84541.289 | L48: =('Income Statement'!K10*Assumptions!K22)/365 -> 92995.418 | M48: =('Income Statement'!L10*Assumptions!L22)/365 -> 102294.96 | N48: =('Income Statement'!M10*Assumptions!M22)/365 -> 110811.01 | O48: =('Income Statement'!N10*Assumptions!N22)/365 -> 118490.84 | P48: =('Income Statement'!O10*Assumptions!O22)/365 -> 125327.4 | ... R48: =('Income Statement'!Q10*Assumptions!Q22)/365 -> 136599.42
B49: Other current liabilities | D49: =Historical!D79 -> 44397.9 | E49: =Historical!E79 -> 25866.6 | F49: =Historical!F79 -> 22358.1 | G49: =Historical!G79 -> 25911.6 | H49: =Historical!H79 -> 31176.3 | I49: =H49 -> 31176.3 | J49: =I49 -> 31176.3 | K49: =J49 -> 31176.3 | L49: =K49 -> 31176.3 | M49: =L49 -> 31176.3 | N49: =M49 -> 31176.3 | O49: =N49 -> 31176.3 | P49: =O49 -> 31176.3 | ... R49: =Q49 -> 31176.3
B50: Provisions | D50: =Historical!D80 -> 45826.5 | E50: =Historical!E80 -> 91478.2 | F50: =Historical!F80 -> 53543.8 | G50: =Historical!G80 -> 53575.6 | H50: =Historical!H80 -> 61551.3 | I50: =H50 -> 61551.3 | J50: =I50 -> 61551.3 | K50: =J50 -> 61551.3 | L50: =K50 -> 61551.3 | M50: =L50 -> 61551.3 | N50: =M50 -> 61551.3 | O50: =N50 -> 61551.3 | P50: =O50 -> 61551.3 | ... R50: =Q50 -> 61551.3
B51: Current tax liabilities | D51: =Historical!D81 -> 1790.8 | E51: =Historical!E81 -> 1781.4 | F51: =Historical!F81 -> 3087.1 | G51: =Historical!G81 -> 4117 | H51: =Historical!H81 -> 7331.8 | I51: =H51 -> 7331.8 | J51: =I51 -> 7331.8 | K51: =J51 -> 7331.8 | L51: =K51 -> 7331.8 | M51: =L51 -> 7331.8 | N51: =M51 -> 7331.8 | O51: =N51 -> 7331.8 | P51: =O51 -> 7331.8 | ... R51: =Q51 -> 7331.8
B52: Total current liabilities | D52: =SUM(D46:D51) -> 161456.3 | E52: =SUM(E46:E51) -> 172005.5 | F52: =SUM(F46:F51) -> 199063.8 | G52: =SUM(G46:G51) -> 169837.7 | H52: =SUM(H46:H51) -> 181942.1 | I52: =SUM(I46:I51) -> 189967.53 | J52: =SUM(J46:J51) -> 196954.42 | K52: =SUM(K46:K51) -> 204639.99 | ... R52: =SUM(R46:R51) -> 256698.12
B53: Liabilities linked to held-for-sale assets | D53: =Historical!D83 -> 0 | E53: =Historical!E83 -> 0 | F53: =Historical!F83 -> 6.2 | G53: =Historical!G83 -> 6.3 | H53: =Historical!H83 -> 0 | I53: =H53 -> 0 | J53: =I53 -> 0 | K53: =J53 -> 0 | L53: =K53 -> 0 | M53: =L53 -> 0 | N53: =M53 -> 0 | O53: =N53 -> 0 | P53: =O53 -> 0 | ... R53: =Q53 -> 0
B54: Total Liabilities | D54: =D44+D52+D53 -> 181868.7 | E54: =E44+E52+E53 -> 187337.6 | F54: =F44+F52+F53 -> 214281.2 | G54: =G44+G52+G53 -> 183737.1 | H54: =H44+H52+H53 -> 196146.3 | I54: =I44+I52 -> 204171.73 | J54: =J44+J52 -> 211158.62 | K54: =K44+K52 -> 218844.19 | L54: =L44+L52 -> 227298.32 | M54: =M44+M52 -> 236597.86 | N54: =N44+N52 -> 245113.91 | O54: =O44+O52 -> 252793.74 | P54: =P44+P52 -> 259630.3 | ... R54: =R44+R52 -> 270902.32
B56: TOTAL EQUITY & LIABILITIES | D56: =D35+D54 -> 676667 | E56: =E35+E54 -> 697998.7 | F56: =F35+F54 -> 807435.9 | G56: =G35+G54 -> 854996.5 | H56: =H35+H54 -> 921005.8 | I56: =I35+I54 -> 1004931.4 | J56: =J35+J54 -> 1097125.3 | K56: =K35+K54 -> 1199777.7 | ... R56: =R35+R54 -> 2205503
D57: =IF(D56=D28,"Tallied","Error") -> Tallied | E57: =IF(E56=E28,"Tallied","Error") -> Tallied | F57: =IF(F56=F28,"Tallied","Error") -> Tallied | G57: =IF(G56=G28,"Tallied","Error") -> Tallied | H57: =IF(H56=H28,"Tallied","Error") -> Tallied | I57: =IF(I56=I28,"Tallied","Error") -> Tallied | J57: =IF(J56=J28,"Tallied","Error") -> Tallied | K57: =IF(K56=K28,"Tallied","Error") -> Tallied | ... R57: =IF(R56=R28,"Tallied","Error") -> Tallied

Sheet Income Statement
N6: (Amounts in ₹MM unless otherwise stated)
C7: Historical | H7: Forecasting
B8: Particulars | C8: 44286 | D8: 44651 | E8: 45016 | F8: 45382 | G8: 45747 | H8: 46112 | I8: 46477 | J8: 46843 | K8: 47208 | L8: 47573 | M8: =L8+365 -> 47938 | N8: =M8+365 -> 48303 | O8: =N8+365 -> 48668 | P8: =O8+365 -> 49033 | Q8: =P8+365 -> 49398
B9: Sales | C9: =Historical!D10 -> 334981.4 | D9: =Historical!E10 -> 386544.9 | E9: =Historical!F10 -> 438856.8 | F9: =Historical!G10 -> 484968.5 | G9: =Historical!H10 -> 525784.4 | H9: =G9*(1+Assumptions!H10) -> 578362.84 | I9: =H9*(1+Assumptions!I10) -> 636199.12 | J9: =I9*(1+Assumptions!J10) -> 699819.04 | K9: =J9*(1+Assumptions!K10) -> 769800.94 | L9: =K9*(1+Assumptions!L10) -> 846781.03 | M9: =L9*(1+Assumptions!M10) -> 917275.56 | N9: =M9*(1+Assumptions!N10) -> 980847.91 | O9: =N9*(1+Assumptions!O10) -> 1037439.8 | ... Q9: =P9*(1+Assumptions!Q10) -> 1130747.8
B10: Less: COGS | C10: =Historical!D14+Historical!D15+Historical!D16 -> 86900.8 | D10: =Historical!E14+Historical!E15+Historical!E16 -> 103515.4 | E10: =Historical!F14+Historical!F15+Historical!F16 -> 106621.6 | F10: =Historical!G14+Historical!G15+Historical!G16 -> 106626.1 | G10: =Historical!H14+Historical!H15+Historical!H16 -> 107473.6 | H10: =H9*Assumptions!H11 -> 138163.66 | I10: =I9*Assumptions!I11 -> 151980.02 | J10: =J9*Assumptions!J11 -> 167178.02 | K10: =K9*Assumptions!K11 -> 183895.83 | L10: =L9*Assumptions!L11 -> 202285.41 | M10: =M9*Assumptions!M11 -> 219125.67 | N10: =N9*Assumptions!N11 -> 234312.31 | O10: =O9*Assumptions!O11 -> 247831.41 | ... Q10: =Q9*Assumptions!Q11 -> 270121.52
B11: Groos Profit | C11: =C9-C10 -> 248080.6 | D11: =D9-D10 -> 283029.5 | E11: =E9-E10 -> 332235.2 | F11: =F9-F10 -> 378342.4 | G11: =G9-G10 -> 418310.8 | H11: =H9-H10 -> 440199.18 | I11: =I9-I10 -> 484219.1 | J11: =J9-J10 -> 532641.01 | ... Q11: =Q9-Q10 -> 860626.28
B12: Less: Employee Cost | C12: =Historical!D17 -> 68622.3 | D12: =Historical!E17 -> 73008.3 | E12: =Historical!F17 -> 82960.3 | F12: =Historical!G17 -> 94290.6 | G12: =Historical!H17 -> 99731.2 | H12: ='Income Statement'!H9*Assumptions!H12 -> 111840.62 | I12: ='Income Statement'!I9*Assumptions!I12 -> 123024.68 | J12: ='Income Statement'!J9*Assumptions!J12 -> 135327.15 | K12: ='Income Statement'!K9*Assumptions!K12 -> 148859.86 | L12: ='Income Statement'!L9*Assumptions!L12 -> 163745.85 | M12: ='Income Statement'!M9*Assumptions!M12 -> 177377.69 | N12: ='Income Statement'!N9*Assumptions!N12 -> 189670.96 | O12: ='Income Statement'!O9*Assumptions!O12 -> 200614.39 | ... Q12: ='Income Statement'!Q9*Assumptions!Q12 -> 218657.77
B13: Less: Selling, admin and other expenses | C13: =Historical!D20 -> 94781.1 | D13: =Historical!E20 -> 107583.6 | E13: =Historical!F20 -> 131546 | F13: =Historical!G20 -> 154181.8 | G13: =Historical!H20 -> 167718 | H13: =H9*Assumptions!H13 -> 173268.25 | I13: =I9*Assumptions!I13 -> 190595.07 | J13: =J9*Assumptions!J13 -> 209654.58 | K13: =K9*Assumptions!K13 -> 230620.04 | L13: =L9*Assumptions!L13 -> 253682.04 | M13: =M9*Assumptions!M13 -> 274801.07 | N13: =N9*Assumptions!N13 -> 293846.33 | O13: =O9*Assumptions!O13 -> 310800.37 | ... Q13: =Q9*Assumptions!Q13 -> 338753.94
B14: EBITDA | C14: =C11-C12-C13 -> 84677.2 | D14: =D11-D12-D13 -> 102437.6 | E14: =E11-E12-E13 -> 117728.9 | F14: =F11-F12-F13 -> 129870 | G14: =G11-G12-G13 -> 150861.6 | H14: =H11-H12-H13 -> 155090.32 | I14: =I11-I12-I13 -> 170599.35 | J14: =J11-J12-J13 -> 187659.28 | ... Q14: =Q11-Q12-Q13 -> 303214.56
B15: Less: Depreciation & Ammotization | C15: =Historical!D19 -> 20799.5 | D15: =Historical!E19 -> 21437.4 | E15: =Historical!F19 -> 25294.3 | F15: =Historical!G19 -> 25566.4 | G15: =Historical!H19 -> 25753.9 | H15: =Schedules!H20 -> 25612.347 | I15: =Schedules!I20 -> 25204.79 | J15: =Schedules!J20 -> 25181.207 | K15: =Schedules!K20 -> 24942.761 | L15: =Schedules!L20 -> 25045.007 | M15: =Schedules!M20 -> 24902.939 | N15: =Schedules!N20 -> 25078.044 | O15: =Schedules!O20 -> 24990.448 | ... Q15: =Schedules!Q20 -> 25242.1
B16: EBIT | C16: =C14-C15 -> 63877.7 | D16: =D14-D15 -> 81000.2 | E16: =E14-E15 -> 92434.6 | F16: =F14-F15 -> 104303.6 | G16: =G14-G15 -> 125107.7 | H16: =H14-H15 -> 129477.97 | I16: =I14-I15 -> 145394.56 | J16: =J14-J15 -> 162478.08 | ... Q16: =Q14-Q15 -> 277972.46
B17: Less: Interest | C17: =Historical!D18 -> 1414.3 | D17: =Historical!E18 -> 1273.5 | E17: =Historical!F18 -> 1720 | F17: =Historical!G18 -> 2384.7 | G17: =Historical!H18 -> 2313.6 | H17: =Schedules!H27 -> 1520.0447 | I17: =Schedules!I27 -> 1520.0447 | J17: =Schedules!J27 -> 1520.0447 | K17: =Schedules!K27 -> 1520.0447 | L17: =Schedules!L27 -> 1520.0447 | M17: =Schedules!M27 -> 1520.0447 | N17: =Schedules!N27 -> 1520.0447 | O17: =Schedules!O27 -> 1520.0447 | ... Q17: =Schedules!Q27 -> 1520.0447
B18: Add: Other Income | C18: =Historical!D11-Historical!D21-Historical!D24 -> -34469.7 | D18: =Historical!E11-Historical!E21-Historical!E24 -> -34913.5 | E18: =Historical!F11-Historical!F21-Historical!F24 -> 3369.7 | F18: =Historical!G11-Historical!G21-Historical!G24 -> 8960 | G18: =Historical!H11-Historical!H21-Historical!H24 -> 14727.2 | H18: =H9*Assumptions!H17 -> 10442.099 | I18: =I9*Assumptions!I17 -> 11486.309 | J18: =J9*Assumptions!J17 -> 12634.94 | K18: =K9*Assumptions!K17 -> 13898.434 | L18: =L9*Assumptions!L17 -> 15288.278 | M18: =M9*Assumptions!M17 -> 16561.027 | N18: =N9*Assumptions!N17 -> 17708.799 | O18: =O9*Assumptions!O17 -> 18730.542 | ... Q18: =Q9*Assumptions!Q17 -> 20415.179
B19: Profit before tax | C19: =C16-C17+C18 -> 27993.7 | D19: =D16-D17+D18 -> 44813.2 | E19: =E16-E17+E18 -> 94084.3 | F19: =F16-F17+F18 -> 110878.9 | G19: =G16-G17+G18 -> 137521.3 | H19: =H16-H17+H18 -> 138400.02 | I19: =I16-I17+I18 -> 155360.82 | J19: =J16-J17+J18 -> 173592.97 | ... Q19: =Q16-Q17+Q18 -> 296867.6
B20: Less: Tax | C20: =Historical!D30 -> 5146.9 | D20: =Historical!E30 -> 10755 | E20: =Historical!F30 -> 8475.9 | F20: =Historical!G30 -> 14394.5 | G20: =Historical!H30 -> 27720.3 | H20: =H19*Assumptions!H18 -> 28176.4 | I20: =I19*Assumptions!I18 -> 31629.392 | J20: =J19*Assumptions!J18 -> 35694.627 | K20: =K19*Assumptions!K18 -> 39862.157 | L20: =L19*Assumptions!L18 -> 44815.199 | M20: =M19*Assumptions!M18 -> 49034.858 | N20: =N19*Assumptions!N18 -> 53304.97 | O20: =O19*Assumptions!O18 -> 56720.774 | ... Q20: =Q19*Assumptions!Q18 -> 62892.321
B21: Share of (loss)/gain of associates or JV | C21: =Historical!D31 -> -123.3 | D21: =Historical!E31 -> -165.4 | E21: =Historical!F31 -> -479 | F21: =Historical!G31 -> -384.1 | G21: =Historical!H31 -> -153.5 | H21: =H9*Assumptions!H19 -> -343.70955 | I21: =I9*Assumptions!I19 -> -378.0805 | J21: =J9*Assumptions!J19 -> -415.88855 | K21: =K9*Assumptions!K19 -> -457.47741 | L21: =L9*Assumptions!L19 -> -503.22515 | M21: =M9*Assumptions!M19 -> -545.11864 | N21: =N9*Assumptions!N19 -> -582.89843 | O21: =O9*Assumptions!O19 -> -616.52988 | ... Q21: =Q9*Assumptions!Q19 -> -671.98095
B22: Net profit | C22: =C19-C20+C21 -> 22723.5 | D22: =D19-D20+D21 -> 33892.8 | E22: =E19-E20+E21 -> 85129.4 | F22: =F19-F20+F21 -> 96100.3 | G22: =G19-G20+G21 -> 109647.5 | H22: =H19-H20+H21 -> 109879.92 | I22: =I19-I20+I21 -> 123353.35 | J22: =J19-J20+J21 -> 137482.46 | ... Q22: =Q19-Q20+Q21 -> 233303.29

Sheet CFS
O6: (Amounts in ₹MM unless otherwise stated)
D7: Historical | I7: Forecasting
B8: Particulars | D8: 44286 | E8: 44651 | F8: 45016 | G8: 45382 | H8: 45747 | I8: 46112 | J8: 46477 | K8: 46843 | L8: 47208 | M8: 47573 | N8: =M8+365 -> 47938 | O8: =N8+365 -> 48303 | P8: =O8+365 -> 48668 | Q8: =P8+365 -> 49033 | R8: =Q8+365 -> 49398
B9: =Historical!B91 -> A. Cash Flow from Operating Activities
B10: =Historical!B92 -> Profit before tax | D10: =Historical!D92 -> 27993.7 | E10: =Historical!E92 -> 44813.2 | F10: =Historical!F92 -> 94084.3 | G10: =Historical!G92 -> 110878.9 | H10: =Historical!H92 -> 137521.3 | I10: ='Income Statement'!H19 -> 138400.02 | J10: ='Income Statement'!I19 -> 155360.82 | K10: ='Income Statement'!J19 -> 173592.97 | L10: ='Income Statement'!K19 -> 193860.84 | M10: ='Income Statement'!L19 -> 215790.96 | N10: ='Income Statement'!M19 -> 236109.17 | O10: ='Income Statement'!N19 -> 254129.02 | P10: ='Income Statement'!O19 -> 270413.7 | ... R10: ='Income Statement'!Q19 -> 296867.6
B11: =Historical!B93 -> Depreciation & amortisation | D11: =Historical!D93 -> 20799.5 | E11: =Historical!E93 -> 21437.4 | F11: =Historical!F93 -> 25294.3 | G11: =Historical!G93 -> 25566.4 | H11: =Historical!H93 -> 25753.9 | I11: ='Income Statement'!H15 -> 25612.347 | J11: ='Income Statement'!I15 -> 25204.79 | K11: ='Income Statement'!J15 -> 25181.207 | L11: ='Income Statement'!K15 -> 24942.761 | M11: ='Income Statement'!L15 -> 25045.007 | N11: ='Income Statement'!M15 -> 24902.939 | O11: ='Income Statement'!N15 -> 25078.044 | P11: ='Income Statement'!O15 -> 24990.448 | ... R11: ='Income Statement'!Q15 -> 25242.1
B12: =Historical!B94 -> Finance costs | D12: =Historical!D94 -> 1414.3 | E12: =Historical!E94 -> 1273.5 | F12: =Historical!F94 -> 1720 | G12: =Historical!G94 -> 2384.7 | H12: =Historical!H94 -> 2313.6 | I12: ='Income Statement'!H17 -> 1520.0447 | J12: ='Income Statement'!I17 -> 1520.0447 | K12: ='Income Statement'!J17 -> 1520.0447 | L12: ='Income Statement'!K17 -> 1520.0447 | M12: ='Income Statement'!L17 -> 1520.0447 | N12: ='Income Statement'!M17 -> 1520.0447 | O12: ='Income Statement'!N17 -> 1520.0447 | P12: ='Income Statement'!O17 -> 1520.0447 | ... R12: ='Income Statement'!Q17 -> 1520.0447
B13: =Historical!B96 -> Other adjustments (net) | D13: =Historical!D95+Historical!D96 -> -4115.3 | E13: =Historical!E95+Historical!E96 -> -2961.4 | F13: =Historical!F95+Historical!F96 -> 211.3 | G13: =Historical!G95+Historical!G96 -> -12407.1 | H13: =Historical!H95+Historical!H96 -> -16863.9 | I13: =-'Income Statement'!H18+'Income Statement'!H21 -> -10785.809 | J13: =-'Income Statement'!I18+'Income Statement'!I21 -> -11864.39 | K13: =-'Income Statement'!J18+'Income Statement'!J21 -> -13050.829 | L13: =-'Income Statement'!K18+'Income Statement'!K21 -> -14355.911 | M13: =-'Income Statement'!L18+'Income Statement'!L21 -> -15791.503 | N13: =-'Income Statement'!M18+'Income Statement'!M21 -> -17106.145 | O13: =-'Income Statement'!N18+'Income Statement'!N21 -> -18291.697 | P13: =-'Income Statement'!O18+'Income Statement'!O21 -> -19347.072 | ... R13: =-'Income Statement'!Q18+'Income Statement'!Q21 -> -21087.16
B14: =Historical!B97 -> Operating profit before WC changes | D14: =SUM(D10:D13) -> 46092.2 | E14: =SUM(E10:E13) -> 64562.7 | F14: =SUM(F10:F13) -> 121309.9 | G14: =SUM(G10:G13) -> 126422.9 | H14: =SUM(H10:H13) -> 148724.9 | I14: =SUM(I10:I13) -> 154746.61 | J14: =SUM(J10:J13) -> 170221.27 | K14: =SUM(K10:K13) -> 187243.4 | ... R14: =SUM(R10:R13) -> 302542.58
B15: =Historical!B98 -> Working Capital Changes
B16: =Historical!B99 -> Inventories | D16: =Historical!D99 -> -10802.9 | E16: =Historical!E99 -> 3069.5 | F16: =Historical!F99 -> -12022 | G16: =Historical!G99 -> 5988.1 | H16: =Historical!H99 -> -1839.7 | I16: ='Balance Sheet'!H18-'Balance Sheet'!I18 -> -29349.118 | J16: ='Balance Sheet'!I18-'Balance Sheet'!J18 -> -13178.242 | K16: ='Balance Sheet'!J18-'Balance Sheet'!K18 -> -14496.066 | L16: ='Balance Sheet'!K18-'Balance Sheet'!L18 -> -15945.673 | M16: ='Balance Sheet'!L18-'Balance Sheet'!M18 -> -17540.24 | N16: ='Balance Sheet'!M18-'Balance Sheet'!N18 -> -16062.475 | O16: ='Balance Sheet'!N18-'Balance Sheet'!O18 -> -14485.23 | P16: ='Balance Sheet'!O18-'Balance Sheet'!P18 -> -12894.707 | ... R16: ='Balance Sheet'!Q18-'Balance Sheet'!R18 -> -9906.4044
B17: =Historical!B100 -> Trade receivables | D17: =Historical!D100 -> 937.3 | E17: =Historical!E100 -> -13422.6 | F17: =Historical!F100 -> -9531.7 | G17: =Historical!G100 -> 3528.9 | H17: =Historical!H100 -> -16020.5 | I17: ='Balance Sheet'!H20-'Balance Sheet'!I20 -> -18210.041 | J17: ='Balance Sheet'!I20-'Balance Sheet'!J20 -> -14867.114 | K17: ='Balance Sheet'!J20-'Balance Sheet'!K20 -> -16353.826 | L17: ='Balance Sheet'!K20-'Balance Sheet'!L20 -> -17989.208 | M17: ='Balance Sheet'!L20-'Balance Sheet'!M20 -> -19788.129 | N17: ='Balance Sheet'!M20-'Balance Sheet'!N20 -> -18120.979 | O17: ='Balance Sheet'!N20-'Balance Sheet'!O20 -> -16341.601 | P17: ='Balance Sheet'!O20-'Balance Sheet'!P20 -> -14547.243 | ... R17: ='Balance Sheet'!Q20-'Balance Sheet'!R20 -> -11175.971
B18: =Historical!B101 -> Other assets | D18: =Historical!D101 -> 1166.2 | E18: =Historical!E101 -> 141.1 | F18: =Historical!F101 -> -2158.1 | G18: =Historical!G101 -> -3839 | H18: =Historical!H101 -> -593.2 | I18: =-(SUM('Balance Sheet'!I19,'Balance Sheet'!I23:I25)-SUM('Balance Sheet'!H19,'Balance Sheet'!H23:H25)) -> 0 | J18: =-(SUM('Balance Sheet'!J19,'Balance Sheet'!J23:J25)-SUM('Balance Sheet'!I19,'Balance Sheet'!I23:I25)) -> 0 | K18: =-(SUM('Balance Sheet'!K19,'Balance Sheet'!K23:K25)-SUM('Balance Sheet'!J19,'Balance Sheet'!J23:J25)) -> 0 | L18: =-(SUM('Balance Sheet'!L19,'Balance Sheet'!L23:L25)-SUM('Balance Sheet'!K19,'Balance Sheet'!K23:K25)) -> 0 | M18: =-(SUM('Balance Sheet'!M19,'Balance Sheet'!M23:M25)-SUM('Balance Sheet'!L19,'Balance Sheet'!L23:L25)) -> 0 | N18: =-(SUM('Balance Sheet'!N19,'Balance Sheet'!N23:N25)-SUM('Balance Sheet'!M19,'Balance Sheet'!M23:M25)) -> 0 | O18: =-(SUM('Balance Sheet'!O19,'Balance Sheet'!O23:O25)-SUM('Balance Sheet'!N19,'Balance Sheet'!N23:N25)) -> 0 | P18: =-(SUM('Balance Sheet'!P19,'Balance Sheet'!P23:P25)-SUM('Balance Sheet'!O19,'Balance Sheet'!O23:O25)) -> 0 | ... R18: =-(SUM('Balance Sheet'!R19,'Balance Sheet'!R23:R25)-SUM('Balance Sheet'!Q19,'Balance Sheet'!Q23:Q25)) -> 0
B19: =Historical!B102 -> Trade payables | D19: =Historical!D102 -> 3814.6 | E19: =Historical!E102 -> 3699.2 | F19: =Historical!F102 -> 11823.7 | G19: =Historical!G102 -> 2497.2 | H19: =Historical!H102 -> 5279.7 | I19: ='Balance Sheet'!I48-'Balance Sheet'!H48 -> 8025.4336 | J19: ='Balance Sheet'!J48-'Balance Sheet'!I48 -> 6986.8834 | K19: ='Balance Sheet'!K48-'Balance Sheet'!J48 -> 7685.5717 | L19: ='Balance Sheet'!L48-'Balance Sheet'!K48 -> 8454.1289 | M19: ='Balance Sheet'!M48-'Balance Sheet'!L48 -> 9299.5418 | N19: ='Balance Sheet'!N48-'Balance Sheet'!M48 -> 8516.0554 | O19: ='Balance Sheet'!O48-'Balance Sheet'!N48 -> 7679.8266 | P19: ='Balance Sheet'!P48-'Balance Sheet'!O48 -> 6836.5581 | ... R19: ='Balance Sheet'!R48-'Balance Sheet'!Q48 -> 5252.2099
B20: =Historical!B103 -> Other liabilities | D20: =Historical!D103 -> 24983.5 | E20: =Historical!E103 -> -23333.5 | F20: =Historical!F103 -> -6691.5 | G20: =Historical!G103 -> 2409.2 | H20: =Historical!H103 -> 1820.3 | I20: =(SUM('Balance Sheet'!I46,'Balance Sheet'!I47,'Balance Sheet'!I49,'Balance Sheet'!I51)-SUM('Balance Sheet'!H46,'Balance Sheet'!H47,'Balance Sheet'!H49,'Balance Sheet'!H51)) -> 0 | J20: =(SUM('Balance Sheet'!J46,'Balance Sheet'!J47,'Balance Sheet'!J49,'Balance Sheet'!J51)-SUM('Balance Sheet'!I46,'Balance Sheet'!I47,'Balance Sheet'!I49,'Balance Sheet'!I51)) -> 0 | K20: =(SUM('Balance Sheet'!K46,'Balance Sheet'!K47,'Balance Sheet'!K49,'Balance Sheet'!K51)-SUM('Balance Sheet'!J46,'Balance Sheet'!J47,'Balance Sheet'!J49,'Balance Sheet'!J51)) -> 0 | L20: =(SUM('Balance Sheet'!L46,'Balance Sheet'!L47,'Balance Sheet'!L49,'Balance Sheet'!L51)-SUM('Balance Sheet'!K46,'Balance Sheet'!K47,'Balance Sheet'!K49,'Balance Sheet'!K51)) -> 0 | M20: =(SUM('Balance Sheet'!M46,'Balance Sheet'!M47,'Balance Sheet'!M49,'Balance Sheet'!M51)-SUM('Balance Sheet'!L46,'Balance Sheet'!L47,'Balance Sheet'!L49,'Balance Sheet'!L51)) -> 0 | N20: =(SUM('Balance Sheet'!N46,'Balance Sheet'!N47,'Balance Sheet'!N49,'Balance Sheet'!N51)-SUM('Balance Sheet'!M46,'Balance Sheet'!M47,'Balance Sheet'!M49,'Balance Sheet'!M51)) -> 0 | O20: =(SUM('Balance Sheet'!O46,'Balance Sheet'!O47,'Balance Sheet'!O49,'Balance Sheet'!O51)-SUM('Balance Sheet'!N46,'Balance Sheet'!N47,'Balance Sheet'!N49,'Balance Sheet'!N51)) -> 0 | P20: =(SUM('Balance Sheet'!P46,'Balance Sheet'!P47,'Balance Sheet'!P49,'Balance Sheet'!P51)-SUM('Balance Sheet'!O46,'Balance Sheet'!O47,'Balance Sheet'!O49,'Balance Sheet'!O51)) -> 0 | ... R20: =(SUM('Balance Sheet'!R46,'Balance Sheet'!R47,'Balance Sheet'!R49,'Balance Sheet'!R51)-SUM('Balance Sheet'!Q46,'Balance Sheet'!Q47,'Balance Sheet'!Q49,'Balance Sheet'!Q51)) -> 0
B21: =Historical!B104 -> Provisions | D21: =Historical!D104 -> 5542.2 | E21: =Historical!E104 -> 45436.8 | F21: =Historical!F104 -> -38038.6 | G21: =Historical!G104 -> 36.9 | H21: =Historical!H104 -> 8117.8 | I21: ='Balance Sheet'!I50-'Balance Sheet'!H50 -> 0 | J21: ='Balance Sheet'!J50-'Balance Sheet'!I50 -> 0 | K21: ='Balance Sheet'!K50-'Balance Sheet'!J50 -> 0 | L21: ='Balance Sheet'!L50-'Balance Sheet'!K50 -> 0 | M21: ='Balance Sheet'!M50-'Balance Sheet'!L50 -> 0 | N21: ='Balance Sheet'!N50-'Balance Sheet'!M50 -> 0 | O21: ='Balance Sheet'!O50-'Balance Sheet'!N50 -> 0 | P21: ='Balance Sheet'!P50-'Balance Sheet'!O50 -> 0 | ... R21: ='Balance Sheet'!R50-'Balance Sheet'!Q50 -> 0
B22: =Historical!B105 -> Cash from operations | D22: =SUM(D14:D21) -> 71733.1 | E22: =SUM(E14:E21) -> 80153.2 | F22: =SUM(F14:F21) -> 64691.7 | G22: =SUM(G14:G21) -> 137044.2 | H22: =SUM(H14:H21) -> 145489.3 | I22: =SUM(I14:I21) -> 115212.88 | J22: =SUM(J14:J21) -> 149162.8 | K22: =SUM(K14:K21) -> 164079.08 | ... R22: =SUM(R14:R21) -> 286712.42
B23: =Historical!B106 -> Tax paid (net) | D23: =Historical!D106 -> -10029.4 | E23: =Historical!E106 -> 9692.2 | F23: =Historical!F106 -> -15098.4 | G23: =Historical!G106 -> -15694.4 | H23: =Historical!H106 -> -4768.4 | I23: =-'Income Statement'!H20 -> -28176.4 | J23: =-'Income Statement'!I20 -> -31629.392 | K23: =-'Income Statement'!J20 -> -35694.627 | L23: =-'Income Statement'!K20 -> -39862.157 | M23: =-'Income Statement'!L20 -> -44815.199 | N23: =-'Income Statement'!M20 -> -49034.858 | O23: =-'Income Statement'!N20 -> -53304.97 | P23: =-'Income Statement'!O20 -> -56720.774 | ... R23: =-'Income Statement'!Q20 -> -62892.321
B24: =Historical!B107 -> Net Cash from Operating (A) | D24: =D22+D23 -> 61703.7 | E24: =E22+E23 -> 89845.4 | F24: =F22+F23 -> 49593.3 | G24: =G22+G23 -> 121349.8 | H24: =H22+H23 -> 140720.9 | I24: =I22+I23 -> 87036.483 | J24: =J22+J23 -> 117533.4 | K24: =K22+K23 -> 128384.45 | ... R24: =R22+R23 -> 223820.1
B25: =Historical!B108 -> B. Cash Flow from Investing Activities
B26: =Historical!B109 -> Purchase of PP&E | D26: =Historical!D109 -> -11701.3 | E26: =Historical!E109 -> -14950.4 | F26: =Historical!F109 -> -20855.8 | G26: =Historical!G109 -> -22018.1 | H26: =Historical!H109 -> -21285.8 | I26: =-Schedules!H19 -> -24015.375 | J26: =-Schedules!I19 -> -24135.452 | K26: =-Schedules!J19 -> -24256.129 | L26: =-Schedules!K19 -> -24377.41 | M26: =-Schedules!L19 -> -24499.297 | N26: =-Schedules!M19 -> -24621.793 | O26: =-Schedules!N19 -> -24744.902 | P26: =-Schedules!O19 -> -24868.627 | ... R26: =-Schedules!Q19 -> -25117.935
B27: =Historical!B110 -> Sale of PP&E | D27: =Historical!D110 -> 971 | E27: =Historical!E110 -> 606.1 | F27: =Historical!F110 -> 210.1 | G27: =Historical!G110 -> 308.4 | H27: =Historical!H110 -> 610.1 | I27: 0 | J27: 0 | K27: 0 | L27: 0 | M27: 0 | N27: 0 | O27: 0 | P27: 0 | Q27: 0 | R27: 0
B28: =Historical!B111 -> Investments (net) | D28: =Historical!D111 -> 11670.6 | E28: =Historical!E111 -> -34485.4 | F28: =Historical!F111 -> -10673.9 | G28: =Historical!G111 -> 10034.3 | H28: =Historical!H111 -> -28911.6 | I28: 0 | J28: 0 | K28: 0 | L28: 0 | M28: 0 | N28: 0 | O28: 0 | P28: 0 | Q28: 0 | R28: 0
B29: =Historical!B112 -> Acquisition/Diaposal of subsidiary (net) | D29: =Historical!D112 -> -616 | E29: =Historical!E112 -> -7157.3 | F29: =Historical!F112 -> -46858.2 | G29: =Historical!G112 -> -1433.2 | H29: =Historical!H112 -> -2728.3 | I29: 0 | J29: 0 | K29: 0 | L29: 0 | M29: 0 | N29: 0 | O29: 0 | P29: 0 | Q29: 0 | R29: 0
B30: =Historical!B113 -> Interest & dividend received | D30: =Historical!D113 -> 2093.6 | E30: =Historical!E113 -> 2101.3 | F30: =Historical!F113 -> 4503.3 | G30: =Historical!G113 -> 7123.4 | H30: =Historical!H113 -> 8697.7 | I30: ='Income Statement'!H18 -> 10442.099 | J30: ='Income Statement'!I18 -> 11486.309 | K30: ='Income Statement'!J18 -> 12634.94 | L30: ='Income Statement'!K18 -> 13898.434 | M30: ='Income Statement'!L18 -> 15288.278 | N30: ='Income Statement'!M18 -> 16561.027 | O30: ='Income Statement'!N18 -> 17708.799 | P30: ='Income Statement'!O18 -> 18730.542 | ... R30: ='Income Statement'!Q18 -> 20415.179
B31: =Historical!B114 -> Other investing flows | D31: =Historical!D114 -> 2944.3 | E31: =Historical!E114 -> -3361.7 | F31: =Historical!F114 -> -5762.3 | G31: =Historical!G114 -> -916.7 | H31: =Historical!H114 -> -9443.7 | I31: 0 | J31: 0 | K31: 0 | L31: 0 | M31: 0 | N31: 0 | O31: 0 | P31: 0 | Q31: 0 | R31: 0
B32: =Historical!B115 -> Net Cash from Investing (B) | D32: =SUM(D26:D31) -> 5362.2 | E32: =SUM(E26:E31) -> -57247.4 | F32: =SUM(F26:F31) -> -79436.8 | G32: =SUM(G26:G31) -> -6901.9 | H32: =SUM(H26:H31) -> -53061.6 | I32: =SUM(I26:I31) -> -13573.276 | J32: =SUM(J26:J31) -> -12649.143 | K32: =SUM(K26:K31) -> -11621.189 | ... R32: =SUM(R26:R31) -> -4702.7561
B33: =Historical!B116 -> C. Cash Flow from Financing Activities
B34: =Historical!B117 -> Borrowings (net) | D34: =Historical!D117 -> -41992.1 | E34: =Historical!E117 -> -27431.3 | F34: =Historical!F117 -> 52601.5 | G34: =Historical!G117 -> -35329.4 | H34: =Historical!H117 -> -9821.4 | I34: =Schedules!H25 -> 0 | J34: =Schedules!I25 -> 0 | K34: =Schedules!J25 -> 0 | L34: =Schedules!K25 -> 0 | M34: =Schedules!L25 -> 0 | N34: =Schedules!M25 -> 0 | O34: =Schedules!N25 -> 0 | P34: =Schedules!O25 -> 0 | ... R34: =Schedules!Q25 -> 0
B35: =Historical!B118 -> Lease payments | D35: =Historical!D118 -> -1177.9 | E35: =Historical!E118 -> -1286.5 | F35: =Historical!F118 -> -1346.2 | G35: =Historical!G118 -> -1231 | H35: =Historical!H118 -> -1345.1 | I35: 0 | J35: 0 | K35: 0 | L35: 0 | M35: 0 | N35: 0 | O35: 0 | P35: 0 | Q35: 0 | R35: 0
B36: =Historical!B119 -> Buyback / NCI | D36: =Historical!D119 -> -1854.2 | E36: =Historical!E119 -> -1857 | F36: =Historical!F119 -> - | G36: =Historical!G119 -> -773.9 | H36: =Historical!H119 -> -28998.5 | I36: 0 | J36: 0 | K36: 0 | L36: 0 | M36: 0 | N36: 0 | O36: 0 | P36: 0 | Q36: 0 | R36: 0
B37: =Historical!B120 -> Finance cost paid | D37: =Historical!D120 -> -1442.5 | E37: =Historical!E120 -> -732.1 | F37: =Historical!F120 -> -992.4 | G37: =Historical!G120 -> -2190.3 | H37: =Historical!H120 -> -2238.2 | I37: =-Schedules!H27 -> -1520.0447 | J37: =-Schedules!I27 -> -1520.0447 | K37: =-Schedules!J27 -> -1520.0447 | L37: =-Schedules!K27 -> -1520.0447 | M37: =-Schedules!L27 -> -1520.0447 | N37: =-Schedules!M27 -> -1520.0447 | O37: =-Schedules!N27 -> -1520.0447 | P37: =-Schedules!O27 -> -1520.0447 | ... R37: =-Schedules!Q27 -> -1520.0447
B38: =Historical!B121 -> Dividend paid | D38: =Historical!D121 -> -15861.7 | E38: =Historical!E121 -> -21691.9 | F38: =Historical!F121 -> -25197.3 | G38: =Historical!G121 -> -29007.1 | H38: =Historical!H121 -> -36173 | I38: =-'Income Statement'!H22*Assumptions!H16 -> -33979.734 | J38: =-'Income Statement'!I22*Assumptions!I16 -> -38146.317 | K38: =-'Income Statement'!J22*Assumptions!J16 -> -42515.662 | L38: =-'Income Statement'!K22*Assumptions!K16 -> -47481.738 | M38: =-'Income Statement'!L22*Assumptions!L16 -> -52717.654 | N38: =-'Income Statement'!M22*Assumptions!M16 -> -57683.082 | O38: =-'Income Statement'!N22*Assumptions!N16 -> -61923.426 | P38: =-'Income Statement'!O22*Assumptions!O16 -> -65892.655 | ... R38: =-'Income Statement'!Q22*Assumptions!Q16 -> -72147.706
B39: =Historical!B122 -> Other financing flows | D39: =Historical!D122 -> 2523.6 | E39: =Historical!E122 -> 1064.2 | F39: =Historical!F122 -> -1304.9 | G39: =Historical!G122 -> 1430.1 | H39: =Historical!H122 -> -482 | I39: 0 | J39: 0 | K39: 0 | L39: 0 | M39: 0 | N39: 0 | O39: 0 | P39: 0 | Q39: 0 | R39: 0
B40: =Historical!B123 -> Net Cash from Financing (C) | D40: =SUM(D34:D39) -> -59804.8 | E40: =SUM(E34:E39) -> -51934.6 | F40: =SUM(F34:F39) -> 23760.7 | G40: =SUM(G34:G39) -> -67101.6 | H40: =SUM(H34:H39) -> -79058.2 | I40: =SUM(I34:I39) -> -35499.779 | J40: =SUM(J34:J39) -> -39666.361 | K40: =SUM(K34:K39) -> -44035.706 | ... R40: =SUM(R34:R39) -> -73667.751
B41: =Historical!B124 -> Net Cash Movement
B42: =Historical!B125 -> Net increase / (decrease) | D42: =+D40+D32+D24 -> 7261.1 | E42: =+E40+E32+E24 -> -19336.6 | F42: =+F40+F32+F24 -> -6082.8 | G42: =+G40+G32+G24 -> 47346.3 | H42: =+H40+H32+H24 -> 8601.1 | I42: =+I40+I32+I24 -> 37963.428 | J42: =+J40+J32+J24 -> 65217.9 | K42: =+K40+K32+K24 -> 72727.554 | ... R42: =+R40+R32+R24 -> 145449.59
B43: =Historical!B126 -> Opening cash | D43: =Historical!D126 -> 56766.1 | E43: =D45 -> 62730.3 | F43: =E45 -> 45082.5 | G43: =F45 -> 46237.3 | H43: =G45 -> 92856.6 | I43: =H45 -> 102687.8 | J43: =I45 -> 140651.23 | K43: =J45 -> 205869.13 | L43: =K45 -> 278596.68 | ... R43: =Q45 -> 932222.13
B44: =Historical!B127 -> Other adjustments | D44: =Historical!D127 -> -1296.9 | E44: =Historical!E127 -> 1688.8 | F44: =Historical!F127 -> 7237.6 | G44: =Historical!G127 -> -727 | H44: =Historical!H127 -> 1230.1 | I44: 0 | J44: 0 | K44: 0 | L44: 0 | M44: 0 | N44: 0 | O44: 0 | P44: 0 | Q44: 0 | R44: 0
B45: =Historical!B128 -> Closing cash | D45: =SUM(D42:D44) -> 62730.3 | E45: =SUM(E42:E44) -> 45082.5 | F45: =SUM(F42:F44) -> 46237.3 | G45: =SUM(G42:G44) -> 92856.6 | H45: =SUM(H42:H44) -> 102687.8 | I45: =SUM(I42:I44) -> 140651.23 | J45: =SUM(J42:J44) -> 205869.13 | K45: =SUM(K42:K44) -> 278596.68 | ... R45: =SUM(R42:R44) -> 1077671.7

Sheet DCF Valuation
N6: (Amounts in ₹MM unless otherwise stated)
B7: Particulars | C7: Historical | H7: Forecasting
C8: ='Income Statement'!C8 -> 44286 | D8: ='Income Statement'!D8 -> 44651 | E8: ='Income Statement'!E8 -> 45016 | F8: ='Income Statement'!F8 -> 45382 | G8: 45747 | H8: 46112 | I8: 46477 | J8: 46843 | K8: 47208 | L8: 47573 | M8: =L8+365 -> 47938 | N8: =M8+365 -> 48303 | O8: =N8+365 -> 48668 | P8: =O8+365 -> 49033 | Q8: =P8+365 -> 49398
B9: Sales | C9: ='Income Statement'!C9 -> 334981.4 | D9: ='Income Statement'!D9 -> 386544.9 | E9: ='Income Statement'!E9 -> 438856.8 | F9: ='Income Statement'!F9 -> 484968.5 | G9: ='Income Statement'!G9 -> 525784.4 | H9: ='Income Statement'!H9 -> 578362.84 | I9: ='Income Statement'!I9 -> 636199.12 | J9: ='Income Statement'!J9 -> 699819.04 | ... Q9: ='Income Statement'!Q9 -> 1130747.8
B10: Less:Cost of Goods Sold | C10: ='Income Statement'!C10 -> 86900.8 | D10: ='Income Statement'!D10 -> 103515.4 | E10: ='Income Statement'!E10 -> 106621.6 | F10: ='Income Statement'!F10 -> 106626.1 | G10: ='Income Statement'!G10 -> 107473.6 | H10: ='Income Statement'!H10 -> 138163.66 | I10: ='Income Statement'!I10 -> 151980.02 | J10: ='Income Statement'!J10 -> 167178.02 | ... Q10: ='Income Statement'!Q10 -> 270121.52
B11: Groos Profit | C11: =C9-C10 -> 248080.6 | D11: =D9-D10 -> 283029.5 | E11: =E9-E10 -> 332235.2 | F11: =F9-F10 -> 378342.4 | G11: =G9-G10 -> 418310.8 | H11: =H9-H10 -> 440199.18 | I11: =I9-I10 -> 484219.1 | J11: =J9-J10 -> 532641.01 | ... Q11: =Q9-Q10 -> 860626.28
B12: Less:Employee Cost | C12: ='Income Statement'!C12 -> 68622.3 | D12: ='Income Statement'!D12 -> 73008.3 | E12: ='Income Statement'!E12 -> 82960.3 | F12: ='Income Statement'!F12 -> 94290.6 | G12: ='Income Statement'!G12 -> 99731.2 | H12: ='Income Statement'!H12 -> 111840.62 | I12: ='Income Statement'!I12 -> 123024.68 | J12: ='Income Statement'!J12 -> 135327.15 | ... Q12: ='Income Statement'!Q12 -> 218657.77
B13: Less:Selling, Admin & Other Expenses | C13: ='Income Statement'!C13 -> 94781.1 | D13: ='Income Statement'!D13 -> 107583.6 | E13: ='Income Statement'!E13 -> 131546 | F13: ='Income Statement'!F13 -> 154181.8 | G13: ='Income Statement'!G13 -> 167718 | H13: ='Income Statement'!H13 -> 173268.25 | I13: ='Income Statement'!I13 -> 190595.07 | J13: ='Income Statement'!J13 -> 209654.58 | ... Q13: ='Income Statement'!Q13 -> 338753.94
B14: Less:Depreciation | C14: ='Income Statement'!C15 -> 20799.5 | D14: ='Income Statement'!D15 -> 21437.4 | E14: ='Income Statement'!E15 -> 25294.3 | F14: ='Income Statement'!F15 -> 25566.4 | G14: ='Income Statement'!G15 -> 25753.9 | H14: ='Income Statement'!H15 -> 25612.347 | I14: ='Income Statement'!I15 -> 25204.79 | J14: ='Income Statement'!J15 -> 25181.207 | ... Q14: ='Income Statement'!Q15 -> 25242.1
B15: EBIT | C15: =C11-C12-C13-C14 -> 63877.7 | D15: =D11-D12-D13-D14 -> 81000.2 | E15: =E11-E12-E13-E14 -> 92434.6 | F15: =F11-F12-F13-F14 -> 104303.6 | G15: =G11-G12-G13-G14 -> 125107.7 | H15: =H11-H12-H13-H14 -> 129477.97 | I15: =I11-I12-I13-I14 -> 145394.56 | J15: =J11-J12-J13-J14 -> 162478.08 | ... Q15: =Q11-Q12-Q13-Q14 -> 277972.46
B16: Less:Tax | C16: =C15*Assumptions!C18 -> 11744.504 | D16: =D15*Assumptions!D18 -> 19439.744 | E16: =E15*Assumptions!E18 -> 8327.2812 | F16: =F15*Assumptions!F18 -> 13540.883 | G16: =G15*Assumptions!G18 -> 25218.079 | H16: =H15*Assumptions!H18 -> 26359.988 | I16: =I15*Assumptions!I18 -> 29600.394 | J16: =J15*Assumptions!J18 -> 33409.154 | ... Q16: =Q15*Assumptions!Q18 -> 58889.328
B17: EBIT(1-Tax) | C17: =C15-C16 -> 52133.196 | D17: =D15-D16 -> 61560.456 | E17: =E15-E16 -> 84107.319 | F17: =F15-F16 -> 90762.717 | G17: =G15-G16 -> 99889.621 | H17: =H15-H16 -> 103117.98 | I17: =I15-I16 -> 115794.17 | J17: =J15-J16 -> 129068.92 | ... Q17: =Q15-Q16 -> 219083.13
B18: (+) Depreciation | C18: =C14 -> 20799.5 | D18: =D14 -> 21437.4 | E18: =E14 -> 25294.3 | F18: =F14 -> 25566.4 | G18: =G14 -> 25753.9 | H18: =H14 -> 25612.347 | I18: =I14 -> 25204.79 | J18: =J14 -> 25181.207 | ... Q18: =Q14 -> 25242.1
B19: (-) Capex | C19: =-Schedules!C19 -> 0 | D19: =-Schedules!D19 -> -22801.3 | E19: =-Schedules!E19 -> -25484.3 | F19: =-Schedules!F19 -> -23585.8 | G19: =-Schedules!G19 -> -24190.1 | H19: =-Schedules!H19 -> -24015.375 | I19: =-Schedules!I19 -> -24135.452 | J19: =-Schedules!J19 -> -24256.129 | ... Q19: =-Schedules!Q19 -> -25117.935
B20: (+/-) Change in Working Capital | C20: =Schedules!C15 -> 25640.9 | D20: =Schedules!D15 -> 15590.5 | E20: =Schedules!E15 -> -56618.2 | F20: =Schedules!F15 -> 10621.3 | G20: =Schedules!G15 -> -3235.6 | H20: =Schedules!H15 -> -39533.726 | I20: =Schedules!I15 -> -21058.473 | J20: =Schedules!J15 -> -23164.32 | ... Q20: =Schedules!Q15 -> -15830.165
B21: Free Cash Flow to firm | C21: =C17+C18-C19+C20 -> 98573.596 | D21: =D17+D18-D19+D20 -> 121389.66 | E21: =E17+E18-E19+E20 -> 78267.719 | F21: =F17+F18-F19+F20 -> 150536.22 | G21: =G17+G18-G19+G20 -> 146598.02 | H21: =H17+H18-H19+H20 -> 113211.98 | I21: =I17+I18-I19+I20 -> 144075.94 | J21: =J17+J18-J19+J20 -> 155341.94 | ... Q21: =Q17+Q18-Q19+Q20 -> 253613
B22: Time Period | C22: - | D22: - | E22: - | F22: - | G22: - | H22: 1 | I22: 2 | J22: =I22+1 -> 3 | K22: =J22+1 -> 4 | L22: =K22+1 -> 5 | M22: =L22+1 -> 6 | N22: =M22+1 -> 7 | O22: =N22+1 -> 8 | P22: =O22+1 -> 9 | Q22: =P22+1 -> 10
B23: Discounting Rate | C23: - | D23: - | E23: - | F23: - | G23: - | H23: =1/(1+$C$27)^H22 -> 0.92419517 | I23: =1/(1+$C$27)^I22 -> 0.8541367 | J23: =1/(1+$C$27)^J22 -> 0.78938901 | K23: =1/(1+$C$27)^K22 -> 0.72954951 | L23: =1/(1+$C$27)^L22 -> 0.67424613 | M23: =1/(1+$C$27)^M22 -> 0.62313501 | N23: =1/(1+$C$27)^N22 -> 0.57589837 | O23: =1/(1+$C$27)^O22 -> 0.53224249 | ... Q23: =1/(1+$C$27)^Q22 -> 0.45460784
B24: PV of FCFF | C24: - | D24: - | E24: - | F24: - | G24: - | H24: =I21*H23 -> 133154.28 | I24: =J21*I23 -> 132683.25 | J24: =K21*J23 -> 132621.29 | K24: =L21*K23 -> 132473.33 | L24: =L21*L23 -> 122431.21 | M24: =M21*M23 -> 124012.81 | N24: =N21*N23 -> 123649.36 | O24: =O21*O23 -> 122067.75 | P24: =P21*P23 -> 119041.31 | Q24: =Q21*Q23 -> 115294.46
B26: Terminal Growth | C26: 0.04 | F26: Calculation of Terminal Value (GGM) | J26: Calculation of Terminal Value (EV/EBITDA)
B27: WACC | C27: =WACC!K38 -> 0.082022539 | F27: FCFF(n+1) | H27: =$Q$21*(1+C26) -> 263757.52 | J27: EV/EBITDA | L27: ='Relative Valuation'!P22 -> 20.35
F28: =B27 -> WACC | H28: =$C$27 -> 0.082022539 | J28: EBITDA | L28: ='Comps Data'!O8 -> 196161.71
B29: Calculation of Equity Value per Share | F29: Terminal Growth Rate | H29: =$C$26 -> 0.04 | J29: Enterprise Value | L29: =L28*L27 -> 3991890.8
B30: PV of FCFF | C30: =SUM(H24:Q24) -> 1257429.1 | F30: Terminal Value | H30: =H27/(H28-H29) -> 6276572.7
B31: PV ofTerminal Value | C31: =L31*Q23 -> 2334062 | J31: Average | L31: =(L29+H30)/2 -> 5134231.8
B32: Value Of Operating Assets | C32: =C30+C31 -> 3591491.1
B33: Add: Cash & other Financial asset | C33: ='Balance Sheet'!H21+'Balance Sheet'!H24+'Balance Sheet'!H22 -> 130722.8 | F33: Current Price | H33: 1840
B34: Less:Debt & Minority Interest | C34: ='Balance Sheet'!H38+'Balance Sheet'!H46+'Balance Sheet'!H34 -> 21375.6 | F34: Target Price | H34: =C37 -> 1542.4658
B35: Value of Equity | C35: =C32+C33-C34 -> 3700838.3 | F35: Potential | H35: =IF(H34>H33,"Upside","Downside") -> Downside
B36: No. of Shares | C36: ='Comps Data'!D8 -> 2399.3
B37: Equity Value per Share | C37: =C35/C36 -> 1542.4658 | F37: Recommendation | H37: =IF(H35="Upside","BUY","IGNORE") -> IGNORE
B40: SENSITIVITY ANALYSIS
D43: Terminal Growth Rate | L43: Terminal Growth Rate
C44: =C37 -> 1542.4658 | D44: 0.03 | E44: 0.035 | F44: 0.04 | G44: 0.045 | H44: 0.05 | K44: =C37 -> 1542.4658 | L44: 0.03 | M44: 0.035 | N44: 0.04 | O44: 0.045 | P44: 0.05
B45: WACC | C45: 0.075 | D45: 1578.9609 | E45: 1655.5344 | F45: 1753.986 | G45: 1885.2548 | H45: 2069.0311 | J45: Exit Multiple | K45: 10 | L45: 1231.2022 | M45: 1284.3399 | N45: 1350.1226 | O45: 1433.6736 | P45: 1543.3159
C46: 0.085 | D46: 1367.6886 | E46: 1413.802 | F46: 1470.1627 | G46: 1540.6137 | H46: 1631.1934 | K46: 15 | L46: 1324.1216 | M46: 1377.2593 | N46: 1443.042 | O46: 1526.593 | P46: 1636.2354
C47: 0.095165878 | D47: 1208.8045 | E47: 1238.5443 | F47: 1273.675 | G47: 1315.8086 | H47: 1367.2709 | K47: 20.35 | L47: 1423.5454 | M47: 1476.6831 | N47: 1542.4658 | O47: 1626.0169 | P47: 1735.6592
C48: 0.105 | D48: 1088.5456 | E48: 1109.0386 | F48: 1132.6845 | G48: 1160.2713 | H48: 1192.8739 | K48: 25 | L48: 1509.9605 | M48: 1563.0982 | N48: 1628.8809 | O48: 1712.4319 | P48: 1822.0743
C49: 0.115 | D49: 989.04951 | E49: 1003.6391 | F49: 1020.174 | G49: 1039.0711 | H49: 1060.8754 | K49: 30 | L49: 1602.88 | M49: 1656.0177 | N49: 1721.8004 | O49: 1805.3514 | P49: 1914.9937
D52: Exit Multiple
C53: =C37 -> 1542.4658 | D53: 10 | E53: 15 | F53: 20.35 | G53: 25 | H53: 30
B54: WACC | C54: 0.075 | D54: 1548.7018 | E54: 1647.8729 | F54: 1753.986 | G54: 1846.2151 | H54: 1945.3862
C55: 0.085 | D55: 1283.033 | E55: 1373.4338 | F55: 1470.1627 | G55: 1554.2355 | H55: 1644.6363
C56: 0.095165878 | D56: 1103.2077 | E56: 1185.5591 | F56: 1273.675 | G56: 1350.2617 | H56: 1432.6131
C57: 0.105 | D57: 976.79484 | E57: 1052.1038 | F57: 1132.6845 | G57: 1202.7219 | H57: 1278.0309
C58: 0.115 | D58: 877.71456 | E58: 946.53557 | F58: 1020.174 | G58: 1084.1776 | H58: 1152.9986

Sheet WACC
B7: Weighted Average Cost of Capital
B8: (Source: Screener.in, Yahoo Finance, Trading Economics ) | H8: (Amounts in ₹MM unless otherwise stated)
B9: Peer Comps
H10: Debt/ | I10: Debt/ | J10: Levered | K10: Unlevered
B11: Name of the Comp | E11: Total Debt | F11: Total Equity | G11: Tax Rate | H11: Equity | I11: Capital | J11: Beta | K11: Beta
B13: ='Comps Data'!B9 -> Divi's Laboratories | E13: =('Comps Data'!E9)*10 -> 9000 | F13: =('Comps Data'!G9)*10 -> 1031400 | G13: ='Comps Data'!N8 -> 0.19486819 | H13: =E13/F13 -> 0.0087260035 | I13: =E13/(E13+F13) -> 0.008650519 | J13: 0.19 | K13: =J13/(1+(1-G13)*H13) -> 0.18867445
B14: ='Comps Data'!B10 -> Torrent Pharmaceuticals | E14: =('Comps Data'!E10)*10 -> 282200 | F14: =('Comps Data'!G10)*10 -> 1274200 | G14: ='Comps Data'!N9 -> 0.24871355 | H14: =E14/F14 -> 0.2214723 | I14: =E14/(E14+F14) -> 0.18131586 | J14: 0.13 | K14: =J14/(1+(1-G14)*H14) -> 0.11145508
B15: ='Comps Data'!B11 -> Lupin | E15: =('Comps Data'!E11)*10 -> 621700 | F15: =('Comps Data'!G11)*10 -> 2615050 | G15: ='Comps Data'!N10 -> 0.28437967 | H15: =E15/F15 -> 0.23773924 | I15: =E15/(E15+F15) -> 0.19207538 | J15: 0.28 | K15: =J15/(1+(1-G15)*H15) -> 0.23928944
B16: ='Comps Data'!B12 -> Dr Reddy's Laboratories | E16: =('Comps Data'!E12)*10 -> 585400 | F16: =('Comps Data'!G12)*10 -> 3468220 | G16: ='Comps Data'!N11 -> 0.17901391 | H16: =E16/F16 -> 0.16878975 | I16: =E16/(E16+F16) -> 0.14441413 | J16: 0.3 | K16: =J16/(1+(1-G16)*H16) -> 0.26348748
B17: ='Comps Data'!B13 -> Cipla | E17: =('Comps Data'!E13)*10 -> 46737 | F17: =('Comps Data'!G13)*10 -> 2835108 | G17: ='Comps Data'!N12 -> 0.26042916 | H17: =E17/F17 -> 0.016485086 | I17: =E17/(E17+F17) -> 0.016217736 | J17: 0.06 | K17: =J17/(1+(1-G17)*H17) -> 0.059277298
B18: ='Comps Data'!B14 -> Zydus Lifesciences | E18: =('Comps Data'!E14)*10 -> 963610 | F18: =('Comps Data'!G14)*10 -> 2608930 | G18: ='Comps Data'!N13 -> 0.22918577 | H18: =E18/F18 -> 0.36935065 | I18: =E18/(E18+F18) -> 0.26972686 | J18: 0.39 | K18: =J18/(1+(1-G18)*H18) -> 0.30357264
B20: Average | G20: =AVERAGE(G15:G18) -> 0.23825213 | H20: =AVERAGE(H15:H18) -> 0.19809118 | I20: =AVERAGE(I15:I18) -> 0.15560853 | J20: =AVERAGE(J15:J18) -> 0.2575 | K20: =AVERAGE(K15:K18) -> 0.21640671
B21: Median | G21: =MEDIAN(G15:G18) -> 0.24480747 | H21: =MEDIAN(H15:H18) -> 0.2032645 | I21: =MEDIAN(I15:I18) -> 0.16824476 | J21: =MEDIAN(J15:J18) -> 0.29 | K21: =MEDIAN(K15:K18) -> 0.25138846
B23: ='Comps Data'!B8 -> Sun Pharma.Inds. | E23: =('Comps Data'!E8)*10 -> 521510 | F23: =('Comps Data'!H8)*10 -> 44147120 | G23: ='Comps Data'!N8 -> 0.19486819 | H23: =E23/F23 -> 0.011813002 | I23: =E23/(E23+F23) -> 0.011675084 | J23: =Beta!K25 -> 0.37075559 | K23: =J23/(1+(1-G23)*H23) -> 0.36726255
B25: Cost of Debt | G25: Cost of Equity
B27: Pre Tax Cost of Debt | E27: =Assumptions!G15 -> 0.081301899 | G27: Risk Free Rate | K27: 0.0689
B28: Tax Rate | E28: =G23 -> 0.19486819 | G28: Equity Risk Premium | K28: ='Market Return'!F7-WACC!K27 -> 0.044430914
B29: Post Tax Cost of Debt | E29: =E27*(1-E28) -> 0.065458745 | G29: Levered Beta | K29: =J23 -> 0.37075559
G30: Cost of Equity | K30: =K27+(K28*K29) -> 0.08537301
B33: Capital Structure | G33: Weighted Average of Capital
E35: Target | J35: Total Cost | K35: Total Weight
B36: Total Debt | E36: =I21 -> 0.16824476 | G36: Debt | J36: =E29 -> 0.065458745 | K36: =E36 -> 0.16824476
B37: Market Capitalisation | E37: =E38-E36 -> 0.83175524 | G37: Equity | J37: =K30 -> 0.08537301 | K37: =E37 -> 0.83175524
B38: Total Capital | E38: 1 | G38: Weighted Average of Capital | K38: =SUMPRODUCT(J36:J37,K36:K37) -> 0.082022539
B40: Notes
B41: 1. Unlevered Beta = Levered Beta/(1+(1-Tax Rate)*Debt/Equity
B42: 2. Levered Beta = Unlevered Beta*(1+(1-Tax Rate)*Debt/Equity

Sheet Beta
B6: (Source: Investing.com)
B7: Nifty 50 Returns | F7: Sun Pharma Returns | J7: Regression Beta
B8: Date | C8: Price | D8: Returns | F8: Date | G8: Price | H8: Returns | J8: SUMMARY OUTPUT
B9: 42520 | C9: 8178.5 | D9: - | F9: 42520 | G9: 812.1 | H9: -
B10: 42521 | C10: 8160.1 | D10: =C10/C9-1 -> -0.0022498013 | F10: 42521 | G10: 762.75 | H10: =G10/G9-1 -> -0.060768378 | J10: Regression Statistics
B11: 42522 | C11: 8179.95 | D11: =C11/C10-1 -> 0.0024325682 | F11: 42522 | G11: 754.55 | H11: =G11/G10-1 -> -0.010750574 | J11: Multiple R | K11: 0.21821599
B12: 42523 | C12: 8218.95 | D12: =C12/C11-1 -> 0.0047677553 | F12: 42523 | G12: 746.75 | H12: =G12/G11-1 -> -0.010337287 | J12: R Square | K12: 0.047618217
B13: 42524 | C13: 8220.8 | D13: =C13/C12-1 -> 0.00022508958 | F13: 42524 | G13: 737.35 | H13: =G13/G12-1 -> -0.012587881 | J13: Adjusted R Square | K13: 0.047233261
B14: 42527 | C14: 8201.05 | D14: =C14/C13-1 -> -0.0024024426 | F14: 42527 | G14: 724.4 | H14: =G14/G13-1 -> -0.017562894 | J14: Standard Error | K14: 0.016915856
B15: 42528 | C15: 8266.45 | D15: =C15/C14-1 -> 0.0079745886 | F15: 42528 | G15: 738.8 | H15: =G15/G14-1 -> 0.01987852 | J15: Observations | K15: 2476
B16: 42529 | C16: 8273.05 | D16: =C16/C15-1 -> 0.00079840802 | F16: 42529 | G16: 738 | H16: =G16/G15-1 -> -0.001082837
B17: 42530 | C17: 8203.6 | D17: =C17/C16-1 -> -0.0083947275 | F17: 42530 | G17: 742.7 | H17: =G17/G16-1 -> 0.0063685637 | J17: ANOVA
B18: 42531 | C18: 8170.05 | D18: =C18/C17-1 -> -0.004089668 | F18: 42531 | G18: 741.4 | H18: =G18/G17-1 -> -0.0017503703 | K18: df | L18: SS | M18: MS | N18: F | O18: Significance F
B19: 42534 | C19: 8110.6 | D19: =C19/C18-1 -> -0.0072765773 | F19: 42534 | G19: 746.45 | H19: =G19/G18-1 -> 0.0068114378 | J19: Regression | K19: 1 | L19: 0.035395634 | M19: 0.035395634 | N19: 123.69774 | O19: 4.4892636e-28
B20: 42535 | C20: 8108.85 | D20: =C20/C19-1 -> -0.00021576702 | F20: 42535 | G20: 753.7 | H20: =G20/G19-1 -> 0.0097126398 | J20: Residual | K20: 2474 | L20: 0.70792565 | M20: 0.00028614618
B21: 42536 | C21: 8206.6 | D21: =C21/C20-1 -> 0.01205473 | F21: 42536 | G21: 751.6 | H21: =G21/G20-1 -> -0.0027862545 | J21: Total | K21: 2475 | L21: 0.74332128
B22: 42537 | C22: 8140.75 | D22: =C22/C21-1 -> -0.0080240294 | F22: 42537 | G22: 754.6 | H22: =G22/G21-1 -> 0.0039914848
B23: 42538 | C23: 8170.2 | D23: =C23/C22-1 -> 0.0036176028 | F23: 42538 | G23: 743.2 | H23: =G23/G22-1 -> -0.015107342 | K23: Coefficients | L23: Standard Error | M23: t Stat | N23: P-value | O23: Lower 95% | P23: Upper 95% | Q23: Lower 95.0% | R23: Upper 95.0%
B24: 42541 | C24: 8238.5 | D24: =C24/C23-1 -> 0.0083596485 | F24: 42541 | G24: 739.85 | H24: =G24/G23-1 -> -0.004507535 | J24: Intercept | K24: 0.00030138215 | L24: 0.00034033824 | M24: 0.88553714 | N24: 0.37595306 | O24: -0.00036599504 | P24: 0.00096875933 | Q24: -0.00036599504 | R24: 0.00096875933
B25: 42542 | C25: 8219.9 | D25: =C25/C24-1 -> -0.0022576925 | F25: 42542 | G25: 736.3 | H25: =G25/G24-1 -> -0.0047982699 | J25: X Variable 1 | K25: 0.37075559 | L25: 0.03333549 | M25: 11.121948 | N25: 4.4892636e-28 | O25: 0.30538725 | P25: 0.43612393 | Q25: 0.30538725 | R25: 0.43612393
B26: 42543 | C26: 8203.7 | D26: =C26/C25-1 -> -0.0019708269 | F26: 42543 | G26: 740.05 | H26: =G26/G25-1 -> 0.0050930327
B27: 42544 | C27: 8270.45 | D27: =C27/C26-1 -> 0.0081365725 | F27: 42544 | G27: 752.6 | H27: =G27/G26-1 -> 0.016958314
B28: 42545 | C28: 8088.6 | D28: =C28/C27-1 -> -0.021987921 | F28: 42545 | G28: 754.75 | H28: =G28/G27-1 -> 0.0028567632
B29: 42548 | C29: 8094.7 | D29: =C29/C28-1 -> 0.00075414781 | F29: 42548 | G29: 773.75 | H29: =G29/G28-1 -> 0.025173899
B30: 42549 | C30: 8127.85 | D30: =C30/C29-1 -> 0.0040952722 | F30: 42549 | G30: 765.1 | H30: =G30/G29-1 -> -0.011179321
B31: 42550 | C31: 8204 | D31: =C31/C30-1 -> 0.0093690213 | F31: 42550 | G31: 770.3 | H31: =G31/G30-1 -> 0.0067964972
B32: 42551 | C32: 8287.75 | D32: =C32/C31-1 -> 0.010208435 | F32: 42551 | G32: 763.1 | H32: =G32/G31-1 -> -0.0093470077
B33: 42552 | C33: 8328.35 | D33: =C33/C32-1 -> 0.0048987964 | F33: 42552 | G33: 763.35 | H33: =G33/G32-1 -> 0.00032761106
B34: 42555 | C34: 8370.7 | D34: =C34/C33-1 -> 0.0050850409 | F34: 42555 | G34: 770.8 | H34: =G34/G33-1 -> 0.0097596122
B35: 42556 | C35: 8335.95 | D35: =C35/C34-1 -> -0.0041513852 | F35: 42556 | G35: 774.5 | H35: =G35/G34-1 -> 0.0048002076
B36: 42558 | C36: 8337.9 | D36: =C36/C35-1 -> 0.00023392655 | F36: 42558 | G36: 778.2 | H36: =G36/G35-1 -> 0.0047772757
B37: 42559 | C37: 8323.2 | D37: =C37/C36-1 -> -0.0017630339 | F37: 42559 | G37: 777.5 | H37: =G37/G36-1 -> -0.00089951169
... B2485: 46169 | C2485: 23907.15 | D2485: =C2485/C2484-1 -> -0.00027390157 | F2485: 46169 | G2485: 1844.3 | H2485: =G2485/G2484-1 -> 0.0019013472

Sheet Market Return
B1: Equity Market Returns
B2: NIFTY 50 Returns (10 years)
B4: (Source: Investing.com )
B5: Date | C5: Price | E5: Yearfrac | F5: =YEARFRAC(B6,B2482) -> 9.9916667
B6: 46169 | C6: 23907.15
B7: 46168 | C7: 23913.7 | E7: Market Return | F7: =_xlfn.RRI(F5,C2482,C6) -> 0.11333091
B8: 46167 | C8: 24031.7
B9: 46164 | C9: 23719.3
B10: 46163 | C10: 23654.7
B11: 46162 | C11: 23603
B12: 46161 | C12: 23618
B13: 46160 | C13: 23649.95
B14: 46157 | C14: 23643.5
B15: 46156 | C15: 23689.6
B16: 46155 | C16: 23412.6
B17: 46154 | C17: 23379.55
B18: 46153 | C18: 23815.85
B19: 46150 | C19: 24176.15
... B2482: 42520 | C2482: 8178.5

Sheet Relative Valuation
O6: (Amounts in ₹MM unless otherwise stated)
B7: Comparable Company Valuation
C9: Market Data | K9: Financials | O9: Market Data
B10: Company | C10: Ticker | D10: Share Price | E10: Share Outstsnding | F10: Equity Value | G10: Net Debt | H10: Cash | I10: Enterprise Value | K10: Revenue | L10: EBITDA | M10: Net Income | O10: EV/Revenue | P10: EV/EBITDA | Q10: P/E
B12: ='Comps Data'!B9 -> Divi's Laboratories | C12: DIVISLAB | D12: ='Comps Data'!C9 -> 6791 | E12: =('Comps Data'!D9) -> 265.5 | F12: =D12*E12 -> 1803010.5 | G12: =('Comps Data'!E9) -> 900 | H12: =('Comps Data'!F9) -> 37150 | I12: =F12+G12-H12 -> 1766760.5 | K12: =('Comps Data'!G9) -> 103140 | L12: =('Comps Data'!O9) -> 38312.681 | M12: =('Comps Data'!I9) -> 21900 | O12: =$I12/$K12 -> 17.129731 | P12: =$I12/$L12 -> 46.114249 | Q12: =F12/M12 -> 82.329247
B13: ='Comps Data'!B10 -> Torrent Pharmaceuticals | C13: TORNTPHARM | D13: ='Comps Data'!C10 -> 4529.1 | E13: =('Comps Data'!D10) -> 338.4 | F13: =D13*E13 -> 1532647.4 | G13: =('Comps Data'!E10) -> 28220 | H13: =('Comps Data'!F10) -> 5794.6 | I13: =F13+G13-H13 -> 1555072.8 | K13: =('Comps Data'!G10) -> 127420 | L13: =('Comps Data'!O10) -> 40722.059 | M13: =('Comps Data'!I10) -> 19150 | O13: =$I13/$K13 -> 12.204307 | P13: =$I13/$L13 -> 38.18748 | Q13: =F13/M13 -> 80.033809
B14: ='Comps Data'!B11 -> Lupin | C14: LUPIN | D14: ='Comps Data'!C11 -> 2275 | E14: =('Comps Data'!D11) -> 457.2 | F14: =D14*E14 -> 1040130 | G14: =('Comps Data'!E11) -> 62170 | H14: =('Comps Data'!F11) -> 31423.3 | I14: =F14+G14-H14 -> 1070876.7 | K14: =('Comps Data'!G11) -> 261505 | L14: =('Comps Data'!O11) -> 79914.194 | M14: =('Comps Data'!I11) -> 32470 | O14: =$I14/$K14 -> 4.0950525 | P14: =$I14/$L14 -> 13.400332 | Q14: =F14/M14 -> 32.033569
B15: ='Comps Data'!B12 -> Dr Reddy's Laboratories | C15: DRREDDY | D15: ='Comps Data'!C12 -> 1320 | E15: =('Comps Data'!D12) -> 834.7 | F15: =D15*E15 -> 1101804 | G15: =('Comps Data'!E12) -> 58540 | H15: =('Comps Data'!F12) -> 24602 | I15: =F15+G15-H15 -> 1135742 | K15: =('Comps Data'!G12) -> 346822 | L15: =('Comps Data'!O12) -> 94845.381 | M15: =('Comps Data'!I12) -> 55490 | O15: =$I15/$K15 -> 3.2747115 | P15: =$I15/$L15 -> 11.974669 | Q15: =F15/M15 -> 19.855902
B16: ='Comps Data'!B13 -> Cipla | C16: CIPLA | D16: ='Comps Data'!C13 -> 1422 | E16: =('Comps Data'!D13) -> 807.8 | F16: =D16*E16 -> 1148691.6 | G16: =('Comps Data'!E13) -> 4673.7 | H16: =('Comps Data'!F13) -> 7998.4 | I16: =F16+G16-H16 -> 1145366.9 | K16: =('Comps Data'!G13) -> 283510.8 | L16: =('Comps Data'!O13) -> 74882.215 | M16: =('Comps Data'!I13) -> 51450 | O16: =$I16/$K16 -> 4.039941 | P16: =$I16/$L16 -> 15.29558 | Q16: =F16/M16 -> 22.326367
B17: ='Comps Data'!B14 -> Zydus Lifesciences | C17: ZYDUSLIFE | D17: ='Comps Data'!C14 -> 1096.45 | E17: =('Comps Data'!D14) -> 1006.2 | F17: =D17*E17 -> 1103248 | G17: =('Comps Data'!E14) -> 96361 | H17: =('Comps Data'!F14) -> 29568 | I17: =F17+G17-H17 -> 1170041 | K17: =('Comps Data'!G14) -> 260893 | L17: =('Comps Data'!O14) -> 85024.354 | M17: =('Comps Data'!I14) -> 46430 | O17: =$I17/$K17 -> 4.4847542 | P17: =$I17/$L17 -> 13.761245 | Q17: =F17/M17 -> 23.761533
B19: Average | O19: =AVERAGE(O12:O17) -> 7.538083 | P19: =AVERAGE(P12:P17) -> 23.122259 | Q19: =AVERAGE(Q12:Q17) -> 43.390071
B20: Median | O20: =MEDIAN(O12:O17) -> 4.2899034 | P20: =MEDIAN(P12:P17) -> 14.528413 | Q20: =MEDIAN(Q12:Q17) -> 27.897551
B22: ='Comps Data'!B8 -> Sun Pharma.Inds. | O22: ='Comps Data'!J8/'Comps Data'!G8 -> 7.0268522 | P22: ='Comps Data'!K8 -> 20.35 | Q22: ='Comps Data'!H8/'Comps Data'!I8 -> 38.546337
B24: Sun Pharmaceuticals Comparable Valuation | O24: EV/Revenue | P24: EV/EBITDA | Q24: P/E
B26: Implied Emterprise Value | O26: =(O20*'Comps Data'!G8) -> 2437055.1 | P26: =(P20*'Comps Data'!O8) -> 2849918.3 | Q26: =Q29-Q28+Q27 -> 3085759.4
B27: ='DCF Valuation'!B34 -> Less:Debt & Minority Interest | O27: ='DCF Valuation'!C34 -> 21375.6 | P27: =O27 -> 21375.6 | Q27: =P27 -> 21375.6
B28: ='DCF Valuation'!B33 -> Add: Cash & other Financial asset | O28: ='DCF Valuation'!C33 -> 130722.8 | P28: =O28 -> 130722.8 | Q28: =P28 -> 130722.8
B29: Implied Market Value | O29: =O26-O27+O28 -> 2546402.3 | P29: =P26-P27 -> 2828542.7 | Q29: =(Q20*'Comps Data'!I8) -> 3195106.6
B30: Shares Outstanding | O30: ='Comps Data'!D8 -> 2399.3 | P30: =O30 -> 2399.3 | Q30: =P30 -> 2399.3
B32: Implied Value Per Share | O32: =O29/O30 -> 1061.3105 | P32: =P29/P30 -> 1178.9033 | Q32: =Q29/Q30 -> 1331.6828

Sheet Comps Data
B6: (Source: NSE India, Screener) | E6: 10 | L6: (Amounts in ₹MM unless otherwise stated)
B7: Name | C7: CMP Rs. | D7: No. Eq. Shares Cr. | E7: Debt Rs.Cr. | F7: Cash End Rs.Cr. | G7: Sales Rs.Cr. | H7: Mar Cap Rs.Cr. | I7: PAT | J7: EV Rs.Cr. | K7: EV / EBITDA | L7: Tax | M7: PBT | N7: Tax Rate | O7: EBITDA
B8: Sun Pharma.Inds. | C8: ='Intro & Core Assumptions'!C11:F11 -> 1840 | D8: 2399.3 | E8: 52151 | F8: 113316.2 | G8: 568090.9 | H8: =C8*D8 -> 4414712 | I8: 114530 | J8: 3991890.8 | K8: 20.35 | L8: 27720 | M8: =L8+I8 -> 142250 | N8: =L8/M8 -> 0.19486819 | O8: =J8/K8 -> 196161.71
B9: Divi's Laboratories | C9: 6791 | D9: 265.5 | E9: 900 | F9: 37150 | G9: 103140 | H9: =C9*D9 -> 1803010.5 | I9: 21900 | J9: 1639016.5 | K9: 42.78 | L9: 7250 | M9: =L9+I9 -> 29150 | N9: =L9/M9 -> 0.24871355 | O9: =J9/K9 -> 38312.681
B10: Torrent Pharmaceuticals | C10: 4529.1 | D10: 338.4 | E10: 28220 | F10: 5794.6 | G10: 127420 | H10: =C10*D10 -> 1532647.4 | I10: 19150 | J10: 1427715.4 | K10: 35.06 | L10: 7610 | M10: =L10+I10 -> 26760 | N10: =L10/M10 -> 0.28437967 | O10: =J10/K10 -> 40722.059
B11: Lupin | C11: 2275 | D11: 457.2 | E11: 62170 | F11: 31423.3 | G11: 261505 | H11: =C11*D11 -> 1040130 | I11: 32470 | J11: 1095623.6 | K11: 13.71 | L11: 7080 | M11: =L11+I11 -> 39550 | N11: =L11/M11 -> 0.17901391 | O11: =J11/K11 -> 79914.194
B12: Dr Reddy's Laboratories | C12: 1320 | D12: 834.7 | E12: 58540 | F12: 24602 | G12: 346822 | H12: =C12*D12 -> 1101804 | I12: 55490 | J12: 1057526 | K12: 11.15 | L12: 19540 | M12: =L12+I12 -> 75030 | N12: =L12/M12 -> 0.26042916 | O12: =J12/K12 -> 94845.381
B13: Cipla | C13: 1422 | D13: 807.8 | E13: 4673.7 | F13: 7998.4 | G13: 283510.8 | H13: =C13*D13 -> 1148691.6 | I13: 51450 | J13: 990691.7 | K13: 13.23 | L13: 15297.6 | M13: =L13+I13 -> 66747.6 | N13: =L13/M13 -> 0.22918577 | O13: =J13/K13 -> 74882.215
B14: Zydus Lifesciences | C14: 1096.45 | D14: 1006.2 | E14: 96361 | F14: 29568 | G14: 260893 | H14: =C14*D14 -> 1103248 | I14: 46430 | J14: 1013490.3 | K14: 11.92 | L14: 14119 | M14: =L14+I14 -> 60549 | N14: =L14/M14 -> 0.23318304 | O14: =J14/K14 -> 85024.354

Sheet Ratio Analysis
B7: Particulars | C7: Historical | H7: Forecasting | R7: Trends | S7: Mean | T7: Median | V7: Interpretation of ratios (As per Base Case)
C8: 44286 | D8: 44651 | E8: 45016 | F8: 45382 | G8: =F8+365 -> 45747 | H8: =G8+365 -> 46112 | I8: =H8+365 -> 46477 | J8: =I8+365 -> 46842 | K8: =J8+365 -> 47207 | L8: =K8+365 -> 47572 | M8: =L8+365 -> 47937 | N8: =M8+365 -> 48302 | ... Q8: =P8+365 -> 49397
B10: Profitability Ratios
B11: Gross Margin | C11: ='Income Statement'!C11/'Income Statement'!C9 -> 0.74058022 | D11: ='Income Statement'!D11/'Income Statement'!D9 -> 0.73220343 | E11: ='Income Statement'!E11/'Income Statement'!E9 -> 0.75704695 | F11: ='Income Statement'!F11/'Income Statement'!F9 -> 0.78013809 | G11: ='Income Statement'!G11/'Income Statement'!G9 -> 0.79559378 | H11: ='Income Statement'!H11/'Income Statement'!H9 -> 0.76111249 | I11: ='Income Statement'!I11/'Income Statement'!I9 -> 0.76111249 | J11: ='Income Statement'!J11/'Income Statement'!J9 -> 0.76111249 | ... Q11: ='Income Statement'!Q11/'Income Statement'!Q9 -> 0.76111249 | S11: =AVERAGE(C11:Q11) -> 0.76111249 | T11: =MEDIAN(C11:Q11) -> 0.76111249 | V11: The Gross Margin showed an overall improving trend during the historical period, increasing from 74.06% in Mar-21 to a peak of 79.56% in Mar-25 before stabilising around 76.11% during forecast period (Mar-26 to Mar-35). The initial improvement indicates efficient management of direct operating costs. The subsequent stabilisation suggests that the company has reached a mature operating stage where cost efficiencies are expected to remain relatively constant. At around 76.11%, the margin indicaes a healthy and sustainable profitability structure in the long term.
B12: EBITDA Margin | C12: ='Income Statement'!C14/'Income Statement'!C9 -> 0.2527818 | D12: ='Income Statement'!D14/'Income Statement'!D9 -> 0.26500828 | E12: ='Income Statement'!E14/'Income Statement'!E9 -> 0.26826268 | F12: ='Income Statement'!F14/'Income Statement'!F9 -> 0.26779059 | G12: ='Income Statement'!G14/'Income Statement'!G9 -> 0.28692673 | H12: ='Income Statement'!H14/'Income Statement'!H9 -> 0.26815402 | I12: ='Income Statement'!I14/'Income Statement'!I9 -> 0.26815402 | J12: ='Income Statement'!J14/'Income Statement'!J9 -> 0.26815402 | ... Q12: ='Income Statement'!Q14/'Income Statement'!Q9 -> 0.26815402 | S12: =AVERAGE(C12:Q12) -> 0.26815402 | T12: =MEDIAN(C12:Q12) -> 0.26815402 | V12: The EBITDA Margin shows an increasing trend from 25.28% in Mar-21 to a peak of 28.69% Mar-25 and then stablised to 26.82% in the forecasted period. The initial improvement indicates better operational efficiency and stronger earnings generation from core business activities. The forecast suggests that the margin will remain stable at around 26.82%, reflecting consistent cost management and sustainable operating performance for a pharma business. The stable trend indicates that the company is expected to maintain healthy profitability in the long term.
B13: EBIT Margin | C13: ='Income Statement'!C16/'Income Statement'!C9 -> 0.19069029 | D13: ='Income Statement'!D16/'Income Statement'!D9 -> 0.20954927 | E13: ='Income Statement'!E16/'Income Statement'!E9 -> 0.21062588 | F13: ='Income Statement'!F16/'Income Statement'!F9 -> 0.21507294 | G13: ='Income Statement'!G16/'Income Statement'!G9 -> 0.23794487 | H13: ='Income Statement'!H16/'Income Statement'!H9 -> 0.2238698 | I13: ='Income Statement'!I16/'Income Statement'!I9 -> 0.22853625 | J13: ='Income Statement'!J16/'Income Statement'!J9 -> 0.23217156 | ... Q13: ='Income Statement'!Q16/'Income Statement'!Q9 -> 0.24583065 | S13: =AVERAGE(C13:Q13) -> 0.22940885 | T13: =MEDIAN(C13:Q13) -> 0.23575244 | V13: The EBIT Margin showing an increasing trend from 19.07% in Mar-21 to 23.79% in Mar-25, reflecting stronger operational profitability and improved control over operating expenses. The forecast indicates a gradual upward movement from 22.18% in Mar-26 to 23.57% in Mar-35, suggesting that operating costs are expected to grow at a slower pace than revenue. The gradual increase reflects improved operational efficiency and economies of scale. At 23.57%, the margin indicates strong earnings generation capability and a sustainable operating structure.
B14: EBT Margin | C14: ='Income Statement'!C19/'Income Statement'!C9 -> 0.083567923 | D14: ='Income Statement'!D19/'Income Statement'!D9 -> 0.11593272 | E14: ='Income Statement'!E19/'Income Statement'!E9 -> 0.21438497 | F14: ='Income Statement'!F19/'Income Statement'!F9 -> 0.22863114 | G14: ='Income Statement'!G19/'Income Statement'!G9 -> 0.26155455 | H14: ='Income Statement'!H19/'Income Statement'!H9 -> 0.23929619 | I14: ='Income Statement'!I19/'Income Statement'!I9 -> 0.24420157 | J14: ='Income Statement'!J19/'Income Statement'!J9 -> 0.24805409 | ... Q14: ='Income Statement'!Q19/'Income Statement'!Q9 -> 0.26254095 | S14: =AVERAGE(C14:Q14) -> 0.22956621 | T14: =MEDIAN(C14:Q14) -> 0.25183243 | V14: The EBT Margin showing a significant improving trend during the historical period, rising from 8.36% in Mar-21 to 26.16% in Mar-25, indicating enhanced profitability before taxation and financing adjustments. The improvement suggests better operational performance coupled with lower financial burden. The forecast indicates a gradual rise from 23.71% in Mar-26 to 25.18% in Mar-35, suggesting stable growth in profitability and controlled financial expenses. At approximately 25.18%, the ratio reflects a healthy earnings profile and a sustainable profit generation capacity.
B15: Net Profit Margin | C15: ='Income Statement'!C22/'Income Statement'!C9 -> 0.06783511 | D15: ='Income Statement'!D22/'Income Statement'!D9 -> 0.087681405 | E15: ='Income Statement'!E22/'Income Statement'!E9 -> 0.1939799 | F15: ='Income Statement'!F22/'Income Statement'!F9 -> 0.19815782 | G15: ='Income Statement'!G22/'Income Statement'!G9 -> 0.2085408 | H15: ='Income Statement'!H22/'Income Statement'!H9 -> 0.1899844 | I15: ='Income Statement'!I22/'Income Statement'!I9 -> 0.19389111 | J15: ='Income Statement'!J22/'Income Statement'!J9 -> 0.1964543 | ... Q15: ='Income Statement'!Q22/'Income Statement'!Q9 -> 0.20632655 | S15: =AVERAGE(C15:Q15) -> 0.1841353 | T15: =MEDIAN(C15:Q15) -> 0.19945573 | V15: The Net Profit Margin showed strong improvement during the historical period, increasing from 6.78% in Mar-21 to 20.85% in Mar-25 and then decreased to 18.82% in Mar-26. The increase reflects strengthening profitability and better cost efficiency, while the moderation suggests normalisation following a period of strong earnings growth. The projected trend indicates gradual stabilisation around 18–20%, suggesting that profitability is expected to remain consistent over time. At around 19.78% in Mar-35, the ratio reflects a strong level of bottom-line profitability.
B16: Return on Capital Employed | C16: ='Income Statement'!C16/('Balance Sheet'!D28-'Balance Sheet'!D52) -> 0.12398364 | D16: ='Income Statement'!D16/('Balance Sheet'!E28-'Balance Sheet'!E52) -> 0.15399477 | E16: ='Income Statement'!E16/('Balance Sheet'!F28-'Balance Sheet'!F52) -> 0.15193761 | F16: ='Income Statement'!F16/('Balance Sheet'!G28-'Balance Sheet'!G52) -> 0.15223274 | G16: ='Income Statement'!G16/('Balance Sheet'!H28-'Balance Sheet'!H52) -> 0.16927864 | H16: ='Income Statement'!H16/('Balance Sheet'!I28-'Balance Sheet'!I52) -> 0.15887572 | I16: ='Income Statement'!I16/('Balance Sheet'!J28-'Balance Sheet'!J52) -> 0.16151884 | J16: ='Income Statement'!J16/('Balance Sheet'!K28-'Balance Sheet'!K52) -> 0.16327195 | ... Q16: ='Income Statement'!Q16/('Balance Sheet'!R28-'Balance Sheet'!R52) -> 0.1426374 | S16: =AVERAGE(C16:Q16) -> 0.1557567 | T16: =MEDIAN(C16:Q16) -> 0.15887572 | V16: The ROCE ratio displayed an improving trend initially, increasing from 12.40% in Mar-21 to 16.93% in Mar-25, indicating better utilisation of capital resources to generate earnings. However, the ratio is projected to moderate gradually over the forecast period from 15.10% in Mar-26 then declining to approximately 11.11% in Mar-35. The decline indicates that capital employed may grow at a faster pace than operating returns as the company expands. Despite moderation, the ratio remains healthy and reflects efficient capital utilisation.
B17: Return on Equity | D17: ='Income Statement'!D22/AVERAGE(('Balance Sheet'!E32+'Balance Sheet'!E33),('Balance Sheet'!D32+'Balance Sheet'!D33)) -> 0.071750535 | E17: ='Income Statement'!E22/AVERAGE(('Balance Sheet'!F32+'Balance Sheet'!F33),('Balance Sheet'!E32+'Balance Sheet'!E33)) -> 0.1637 | F17: ='Income Statement'!F22/AVERAGE(('Balance Sheet'!G32+'Balance Sheet'!G33),('Balance Sheet'!F32+'Balance Sheet'!F33)) -> 0.1606194 | G17: ='Income Statement'!G22/AVERAGE(('Balance Sheet'!H32+'Balance Sheet'!H33),('Balance Sheet'!G32+'Balance Sheet'!G33)) -> 0.16138306 | H17: ='Income Statement'!H22/AVERAGE(('Balance Sheet'!I32+'Balance Sheet'!I33),('Balance Sheet'!H32+'Balance Sheet'!H33)) -> 0.14455405 | I17: ='Income Statement'!I22/AVERAGE(('Balance Sheet'!J32+'Balance Sheet'!J33),('Balance Sheet'!I32+'Balance Sheet'!I33)) -> 0.14672977 | J17: ='Income Statement'!J22/AVERAGE(('Balance Sheet'!K32+'Balance Sheet'!K33),('Balance Sheet'!J32+'Balance Sheet'!J33)) -> 0.14770817 | K17: ='Income Statement'!K22/AVERAGE(('Balance Sheet'!L32+'Balance Sheet'!L33),('Balance Sheet'!K32+'Balance Sheet'!K33)) -> 0.14888354 | ... Q17: ='Income Statement'!Q22/AVERAGE(('Balance Sheet'!R32+'Balance Sheet'!R33),('Balance Sheet'!Q32+'Balance Sheet'!Q33)) -> 0.12601837 | S17: =AVERAGE(C17:Q17) -> 0.14148684 | T17: =MEDIAN(C17:Q17) -> 0.147005 | V17: The ROE ratio showed an improving trend initially, increasing from 7.18% in Mar-22 to 16.37% in Mar-22, indicating stronger returns generated on shareholders’ funds. However, the ratio is projected to moderate gradually over the forecast period from 13.71% in Mar-26 declinig to 9.74% in Mar-35. The decline indicates that the equity base may grow at a faster pace than net earnings as the company expands. Despite moderation, the ratio remains healthy and reflects sustainable shareholder returns.
B18: Return on Assets | D18: ='Income Statement'!D22/AVERAGE('Balance Sheet'!E28,'Balance Sheet'!D28) -> 0.049310607 | E18: ='Income Statement'!E22/AVERAGE('Balance Sheet'!F28,'Balance Sheet'!E28) -> 0.11309611 | F18: ='Income Statement'!F22/AVERAGE('Balance Sheet'!G28,'Balance Sheet'!F28) -> 0.11561408 | G18: ='Income Statement'!G22/AVERAGE('Balance Sheet'!H28,'Balance Sheet'!G28) -> 0.12347675 | H18: ='Income Statement'!H22/AVERAGE('Balance Sheet'!I28,'Balance Sheet'!H28) -> 0.1141054 | I18: ='Income Statement'!I22/AVERAGE('Balance Sheet'!J28,'Balance Sheet'!I28) -> 0.11736443 | J18: ='Income Statement'!J22/AVERAGE('Balance Sheet'!K28,'Balance Sheet'!J28) -> 0.11971115 | K18: ='Income Statement'!K22/AVERAGE('Balance Sheet'!L28,'Balance Sheet'!K28) -> 0.12214558 | ... Q18: ='Income Statement'!Q22/AVERAGE('Balance Sheet'!R28,'Balance Sheet'!Q28) -> 0.10992951 | S18: =AVERAGE(C18:Q18) -> 0.11325512 | T18: =MEDIAN(C18:Q18) -> 0.11781375 | V18: The ROA ratio showed an improving trend initially, increasing from 4.93% in Mar-22 to 12.35% in Mar-24, indicating better utilisation of assets to generate earnings. However, the ratio is projected to decline gradually over the forecast period from 10.83% in Mar-26 declines to 8.50% in Mar-35. The decline indicates that the asset base may grow at a faster pace than net earnings as the company expands. Despite moderation, the ratio remains healthy and reflects efficient asset utilisation.
B20: Efficiency/ Turnover Ratios
B21: Debtor Turnover Ratio | D21: ='Income Statement'!D9/AVERAGE('Balance Sheet'!E20,'Balance Sheet'!D20) -> 3.9334405 | E21: ='Income Statement'!E9/AVERAGE('Balance Sheet'!F20,'Balance Sheet'!E20) -> 3.9839211 | F21: ='Income Statement'!F9/AVERAGE('Balance Sheet'!G20,'Balance Sheet'!F20) -> 4.2751328 | G21: ='Income Statement'!G9/AVERAGE('Balance Sheet'!H20,'Balance Sheet'!G20) -> 4.3282487 | H21: ='Income Statement'!H9/AVERAGE('Balance Sheet'!I20,'Balance Sheet'!H20) -> 4.144006 | I21: ='Income Statement'!I9/AVERAGE('Balance Sheet'!J20,'Balance Sheet'!I20) -> 4.0754643 | J21: ='Income Statement'!J9/AVERAGE('Balance Sheet'!K20,'Balance Sheet'!J20) -> 4.0754643 | K21: ='Income Statement'!K9/AVERAGE('Balance Sheet'!L20,'Balance Sheet'!K20) -> 4.0754643 | ... Q21: ='Income Statement'!Q9/AVERAGE('Balance Sheet'!R20,'Balance Sheet'!Q20) -> 3.9664708 | S21: =AVERAGE(C21:Q21) -> 4.0700007 | T21: =MEDIAN(C21:Q21) -> 4.0605697 | V21: The Debtor Turnover Ratio showed a relatively improving trend from 3.93x in Mar-22 to 4.33x in Mar-24, indicating better collection efficiency and faster recovery of receivables. However, the ratio is projected to moderate gradually over the forecast period from 4.05x in Mar-26 to 3.93x in Mar-35. The decline indicates that receivables may grow at a faster pace than revenue as operations expand. Even though the ratio remains stable and reflects manageable collection efficiency.
B22: Creditor Turnover Ratio | D22: ='Income Statement'!D10/AVERAGE('Balance Sheet'!E48,'Balance Sheet'!D48) -> 2.4491991 | E22: ='Income Statement'!E10/AVERAGE('Balance Sheet'!F48,'Balance Sheet'!E48) -> 2.0986728 | F22: ='Income Statement'!F10/AVERAGE('Balance Sheet'!G48,'Balance Sheet'!F48) -> 1.8813903 | G22: ='Income Statement'!G10/AVERAGE('Balance Sheet'!H48,'Balance Sheet'!G48) -> 1.8157944 | H22: ='Income Statement'!H10/AVERAGE('Balance Sheet'!I48,'Balance Sheet'!H48) -> 2.0979624 | I22: ='Income Statement'!I10/AVERAGE('Balance Sheet'!J48,'Balance Sheet'!I48) -> 2.0716372 | J22: ='Income Statement'!J10/AVERAGE('Balance Sheet'!K48,'Balance Sheet'!J48) -> 2.0716372 | K22: ='Income Statement'!K10/AVERAGE('Balance Sheet'!L48,'Balance Sheet'!K48) -> 2.0716372 | ... Q22: ='Income Statement'!Q10/AVERAGE('Balance Sheet'!R48,'Balance Sheet'!Q48) -> 2.0162337 | S22: =AVERAGE(C22:Q22) -> 2.0573405 | T22: =MEDIAN(C22:Q22) -> 2.0640661 | V22: The Creditor Turnover Ratio showed a declining trend initially, decreasing from 2.45x in Mar-22 to 1.82x in Mar-25, indicating a relatively longer payment cycle towards suppliers. However, the ratio is projected to improve slightly at 2.05x in Mar-26 which is suggesting shorter payment period , but in declining trend till Mar-35 at 2.00x. The trend suggests balanced management of payables and healthy supplier relationships. Despite fluctuations, the ratio reflects sustainable working capital management.
B23: Inventory Turnover Ratio | D23: ='Income Statement'!D10/AVERAGE('Balance Sheet'!E18,'Balance Sheet'!D18) -> 1.1505655 | E23: ='Income Statement'!E10/AVERAGE('Balance Sheet'!F18,'Balance Sheet'!E18) -> 1.0930022 | F23: ='Income Statement'!F10/AVERAGE('Balance Sheet'!G18,'Balance Sheet'!F18) -> 1.046311 | G23: ='Income Statement'!G10/AVERAGE('Balance Sheet'!H18,'Balance Sheet'!G18) -> 1.0687712 | H23: ='Income Statement'!H10/AVERAGE('Balance Sheet'!I18,'Balance Sheet'!H18) -> 1.1797983 | I23: ='Income Statement'!I10/AVERAGE('Balance Sheet'!J18,'Balance Sheet'!I18) -> 1.0983474 | J23: ='Income Statement'!J10/AVERAGE('Balance Sheet'!K18,'Balance Sheet'!J18) -> 1.0983474 | K23: ='Income Statement'!K10/AVERAGE('Balance Sheet'!L18,'Balance Sheet'!K18) -> 1.0983474 | ... Q23: ='Income Statement'!Q10/AVERAGE('Balance Sheet'!R18,'Balance Sheet'!Q18) -> 1.0689734 | S23: =AVERAGE(C23:Q23) -> 1.0946784 | T23: =MEDIAN(C23:Q23) -> 1.0916607 | V23: The Inventory Turnover Ratio slightly declined from 1.15x in Mar-22 to 1.07x in Mar-25. This movement indicates that inventory is stucked more days in 2025 than in 2021.But the ratio will slightly improve in Mar-26 at 1.16x after that it is forecasted to decline to 1.06x by Mar-35, suggesting efficient inventory utilisation and stable operational performance in the long term..
B24: Fixed Asset Turnover Ratio | D24: ='Income Statement'!D9/AVERAGE('Balance Sheet'!D11,'Balance Sheet'!E11) -> 3.751703 | E24: ='Income Statement'!E9/AVERAGE('Balance Sheet'!E11,'Balance Sheet'!F11) -> 4.2275491 | F24: ='Income Statement'!F9/AVERAGE('Balance Sheet'!F11,'Balance Sheet'!G11) -> 4.7123895 | G24: ='Income Statement'!G9/AVERAGE('Balance Sheet'!G11,'Balance Sheet'!H11) -> 5.1985134 | H24: ='Income Statement'!H9/AVERAGE('Balance Sheet'!H11,'Balance Sheet'!I11) -> 5.8091355 | I24: ='Income Statement'!I9/AVERAGE('Balance Sheet'!I11,'Balance Sheet'!J11) -> 6.4767753 | J24: ='Income Statement'!J9/AVERAGE('Balance Sheet'!J11,'Balance Sheet'!K11) -> 7.1975221 | K24: ='Income Statement'!K9/AVERAGE('Balance Sheet'!K11,'Balance Sheet'!L11) -> 7.9784242 | ... Q24: ='Income Statement'!Q9/AVERAGE('Balance Sheet'!Q11,'Balance Sheet'!R11) -> 11.963188 | S24: =AVERAGE(C24:Q24) -> 7.7460862 | T24: =MEDIAN(C24:Q24) -> 7.5879732 | V24: The Fixed Asset Turnover Ratio showed a strong improving trend during the historical period, increasing from 3.75x in Mar-22 to 5.20x in Mar-25, indicating better utilisation of fixed assets to generate revenue. The ratio is further projected to improve significantly from 5.55x in Mar-26 to 8.22x in Mar-35. The increase indicates that revenue growth is expected to outpace additions in fixed assets, reflecting improved operational efficiency and stronger asset utilisation. Despite expansion, the ratio reflects healthy fixed asset productivity.
B25: Capital Turnover Ratio | D25: ='Income Statement'!D9/AVERAGE(('Balance Sheet'!E32+'Balance Sheet'!E33),('Balance Sheet'!D32+'Balance Sheet'!D33)) -> 0.81830959 | E25: ='Income Statement'!E9/AVERAGE(('Balance Sheet'!F32+'Balance Sheet'!F33),('Balance Sheet'!E32+'Balance Sheet'!E33)) -> 0.84390183 | F25: ='Income Statement'!F9/AVERAGE(('Balance Sheet'!G32+'Balance Sheet'!G33),('Balance Sheet'!F32+'Balance Sheet'!F33)) -> 0.81056304 | G25: ='Income Statement'!G9/AVERAGE(('Balance Sheet'!H32+'Balance Sheet'!H33),('Balance Sheet'!G32+'Balance Sheet'!G33)) -> 0.77386804 | H25: ='Income Statement'!H9/AVERAGE(('Balance Sheet'!I32+'Balance Sheet'!I33),('Balance Sheet'!H32+'Balance Sheet'!H33)) -> 0.7608733 | I25: ='Income Statement'!I9/AVERAGE(('Balance Sheet'!J32+'Balance Sheet'!J33),('Balance Sheet'!I32+'Balance Sheet'!I33)) -> 0.75676378 | J25: ='Income Statement'!J9/AVERAGE(('Balance Sheet'!K32+'Balance Sheet'!K33),('Balance Sheet'!J32+'Balance Sheet'!J33)) -> 0.75187041 | K25: ='Income Statement'!K9/AVERAGE(('Balance Sheet'!L32+'Balance Sheet'!L33),('Balance Sheet'!K32+'Balance Sheet'!K33)) -> 0.74644907 | ... Q25: ='Income Statement'!Q9/AVERAGE(('Balance Sheet'!R32+'Balance Sheet'!R33),('Balance Sheet'!Q32+'Balance Sheet'!Q33)) -> 0.61077146 | S25: =AVERAGE(C25:Q25) -> 0.73952441 | T25: =MEDIAN(C25:Q25) -> 0.74915974 | V25: The Capital Turnover Ratio showed a declining trend during the historical period, decreasing from 0.82x in Mar-22 to 0.77x in Mar-24, indicating lower efficiency in generating revenue from capital employed. The ratio is further projected to decline gradually from 0.73x in Mar-26 to 0.49x in Mar-35. The decline indicates that capital employed is expected to grow at a faster pace than revenue as the company expands its operations. Despite moderation, the ratio remains stable and reflects sustainable utilisation of capital resources in the long term.
B27: Liquidity & Solvency Ratios
B28: Current Ratio | C28: ='Balance Sheet'!D26/'Balance Sheet'!D52 -> 1.8854687 | D28: ='Balance Sheet'!E26/'Balance Sheet'!E52 -> 2.0356896 | E28: ='Balance Sheet'!F26/'Balance Sheet'!F52 -> 2.0024706 | F28: ='Balance Sheet'!G26/'Balance Sheet'!G52 -> 2.5573303 | G28: ='Balance Sheet'!H26/'Balance Sheet'!H52 -> 2.8907031 | H28: ='Balance Sheet'!I26/'Balance Sheet'!I52 -> 3.2187778 | I28: ='Balance Sheet'!J26/'Balance Sheet'!J52 -> 3.57812 | J28: ='Balance Sheet'!K26/'Balance Sheet'!K52 -> 3.9498829 | ... Q28: ='Balance Sheet'!R26/'Balance Sheet'!R52 -> 7.0757838 | S28: =AVERAGE(C28:Q28) -> 4.108313 | T28: =MEDIAN(C28:Q28) -> 3.9498829 | V28: The Current Ratio showed a strong improving trend during the historical period, increasing from 1.89x in Mar-21 to 2.89x in Mar-25, indicating strengthening short term liquidity and improved ability to meet current obligations. The ratio is further projected to improve significantly from 3.23x in Mar-26 to 6.88x in Mar-35. The continuous increase indicates that current assets are expected to grow at a faster pace than current liabilities, reflecting a very strong liquidity position. At 6.88x, the ratio reflects an extremely comfortable short term financial position.
B29: Quick Ratio | C29: =('Balance Sheet'!D26-'Balance Sheet'!D18)/'Balance Sheet'!D52 -> 1.3282269 | D29: =('Balance Sheet'!E26-'Balance Sheet'!E18)/'Balance Sheet'!E52 -> 1.5126359 | E29: =('Balance Sheet'!F26-'Balance Sheet'!F18)/'Balance Sheet'!F52 -> 1.4743459 | F29: =('Balance Sheet'!G26-'Balance Sheet'!G18)/'Balance Sheet'!G52 -> 1.976288 | G29: =('Balance Sheet'!H26-'Balance Sheet'!H18)/'Balance Sheet'!H52 -> 2.3277037 | H29: =('Balance Sheet'!I26-'Balance Sheet'!I18)/'Balance Sheet'!I52 -> 2.5250676 | I29: =('Balance Sheet'!J26-'Balance Sheet'!J18)/'Balance Sheet'!J52 -> 2.8421088 | J29: =('Balance Sheet'!K26-'Balance Sheet'!K18)/'Balance Sheet'!K52 -> 3.1706768 | ... Q29: =('Balance Sheet'!R26-'Balance Sheet'!R18)/'Balance Sheet'!R52 -> 6.0720925 | S29: =AVERAGE(C29:Q29) -> 3.3452431 | T29: =MEDIAN(C29:Q29) -> 3.1706768 | V29: The Quick Ratio demonstrated a continuous improving trend during the historical period, rising from 1.33x in Mar-21 to 2.33x in Mar-25, indicating improved availability of liquid assets to meet short term liabilities. The ratio is projected to increase further from 2.56x in Mar-26 to 6.06x in Mar-35. The continued rise indicates stronger liquidity management and reduced dependence on inventory for meeting obligations. At 6.06x, the ratio reflects a highly comfortable liquidity position.
B30: Cash Ratio | C30: =('Balance Sheet'!D21+'Balance Sheet'!D22)/'Balance Sheet'!D52 -> 0.39921081 | D30: =('Balance Sheet'!E21+'Balance Sheet'!E22)/'Balance Sheet'!E52 -> 0.29262727 | E30: =('Balance Sheet'!F21+'Balance Sheet'!F22)/'Balance Sheet'!F52 -> 0.28987139 | F30: =('Balance Sheet'!G21+'Balance Sheet'!G22)/'Balance Sheet'!G52 -> 0.61945493 | G30: =('Balance Sheet'!H21+'Balance Sheet'!H22)/'Balance Sheet'!H52 -> 0.62281462 | H30: =('Balance Sheet'!I21+'Balance Sheet'!I22)/'Balance Sheet'!I52 -> 0.79634517 | I30: =('Balance Sheet'!J21+'Balance Sheet'!J22)/'Balance Sheet'!J52 -> 1.0992271 | J30: =('Balance Sheet'!K21+'Balance Sheet'!K22)/'Balance Sheet'!K52 -> 1.4133366 | ... Q30: =('Balance Sheet'!R21+'Balance Sheet'!R22)/'Balance Sheet'!R52 -> 4.2396111 | S30: =AVERAGE(C30:Q30) -> 1.7272173 | T30: =MEDIAN(C30:Q30) -> 1.4133366 | V30: The Cash Ratio showed a strong improving trend during the historical period, increasing from 0.40x in Mar-21 to 0.62x in Mar-25, indicating growth in cash and cash equivalents relative to current liabilities. The ratio is projected to improve significantly from 0.84x in Mar-26 to 4.28x in Mar-35. The increase suggests strong cash accumulation and enhanced financial flexibility. At 4.28x, the ratio reflects a very strong cash position and minimal liquidity risk.
B31: Debt to equity ratio | C31: ='Balance Sheet'!D38/('Balance Sheet'!D32+'Balance Sheet'!D33) -> 0.014090849 | D31: ='Balance Sheet'!E38/('Balance Sheet'!E32+'Balance Sheet'!E33) -> 0.0047888806 | E31: ='Balance Sheet'!F38/('Balance Sheet'!F32+'Balance Sheet'!F33) -> 0 | F31: ='Balance Sheet'!G38/('Balance Sheet'!G32+'Balance Sheet'!G33) -> 2.0890025e-05 | G31: ='Balance Sheet'!H38/('Balance Sheet'!H32+'Balance Sheet'!H33) -> 3.4894338e-05 | H31: ='Balance Sheet'!I38/('Balance Sheet'!I32+'Balance Sheet'!I33) -> 3.1575767e-05 | I31: ='Balance Sheet'!J38/('Balance Sheet'!J32+'Balance Sheet'!J33) -> 2.8529785e-05 | J31: ='Balance Sheet'!K38/('Balance Sheet'!K32+'Balance Sheet'!K33) -> 2.5760175e-05 | ... Q31: ='Balance Sheet'!R38/('Balance Sheet'!R32+'Balance Sheet'!R33) -> 1.3044009e-05 | S31: =AVERAGE(C31:Q31) -> 0.0012763023 | T31: =MEDIAN(C31:Q31) -> 2.0963862e-05 | V31: The Debt to Equity Ratio remained extremely low during the historical and forecast period, ranging between 0.00x and 0.01x, indicating negligible reliance on external borrowings. The consistently low ratio reflects a highly conservative capital structure supported primarily through equity and internal accruals. The stable trend suggests strong financial stability and minimal leverage risk in the long term.
B32: Interest Coverage Ratio | C32: ='Income Statement'!C16/'Income Statement'!C17 -> 45.165594 | D32: ='Income Statement'!D16/'Income Statement'!D17 -> 63.604397 | E32: ='Income Statement'!E16/'Income Statement'!E17 -> 53.741047 | F32: ='Income Statement'!F16/'Income Statement'!F17 -> 43.738667 | G32: ='Income Statement'!G16/'Income Statement'!G17 -> 54.074905 | H32: ='Income Statement'!H16/'Income Statement'!H17 -> 85.180371 | I32: ='Income Statement'!I16/'Income Statement'!I17 -> 95.651503 | J32: ='Income Statement'!J16/'Income Statement'!J17 -> 106.89033 | ... Q32: ='Income Statement'!Q16/'Income Statement'!Q17 -> 182.87124 | S32: =AVERAGE(C32:Q32) -> 108.46033 | T32: =MEDIAN(C32:Q32) -> 106.89033 | V32: The Interest Coverage Ratio showed a strong improving trend during the historical period, increasing from 45.17x in Mar-21 to 54.07x in Mar-25, indicating improved ability to meet interest obligations through operating earnings. The ratio is further projected to improve significantly from 80.54x in Mar-26 to 120.50x in Mar-35. The substantial increase indicates strong earnings growth relative to finance costs and reflects a highly comfortable debt servicing position.

Sheet Summary
B7: Football Field Data
K8: Market
H9: Comps | I9: DCF | J9: 52-week hi/low | K9: Consensus
E10: High | H10: ='Relative Valuation'!Q32 -> 1331.6828 | I10: 1774.49 | J10: 1916.6 | K10: 2392
E11: High | H11: ='Relative Valuation'!Q32 -> 1331.6828 | I11: =I10+0.00022 -> 1774.4902 | J11: =J10+0.0002 -> 1916.6002 | K11: =K10+0.00022 -> 2392.0002
E12: Low | H12: ='Relative Valuation'!O32 -> 1061.3105 | I12: 1293.04 | J12: 1548 | K12: 1550
E13: Low | H13: ='Relative Valuation'!O32 -> 1061.3105 | I13: =I12 -> 1293.04 | J13: =J12+0.0002 -> 1548.0002 | K13: =K12+0.0022 -> 1550.0022
B15: Valuation Summary
J19: = | K19: DCF Base Case Price (1503.43)
J20: = | K20: CMP (1840.00)
